Workbook

Sheet Закупка
B1: комментарий логиста? как в накладной? | C1: Codigo | D1: цена закупки за пачку | E1: сколько пачек купили | F1: внтури пачки штук? | G1: M | H1: P | I1: A | J1: G | K1: B | L1: брак возврат | M1: ok? | O1: ожидаемое кол-во штук товара | P1: новая цена | Q1: цена в базе | R1: фото | S1: название с поиском | T1: Holded артикул | U1: название с holded | V1: codigo de fabricasion | W1: img | X1: цена закупки из базы | Y1: карточка | Z1: карточка товара | AA1: примечания от саши
B2: 45845 | C2: Логист: Саша | P2: 45754 | R2: Бек Офис: Соня
B3: Фактура 1 | C3: 001797 / 2026 | M3: =IF(E3<>"", E3 - SUM(G3:L3), "") | O3: =IF(AND(F3<>"", E3<>""), F3*E3, "") | Z3: {=IF(R4 = "", "", HYPERLINK("https://app.holded.com/products/" & INDEX(products!A:A, MATCH(TEXT(R4, "0"), TEXT(products!B:B, "0"), 0)), "Открыть карточку товара"))} -> #N/A
A4: 1.1 | B4: RANUNCULUS CLOONEY TUAREQ | D4: 1.11 | E4: 3 | F4: 10 | J4: 3 | M4: =IF(E4<>"", E4 - SUM(G4:L4), "") -> 0 | O4: =IF(AND(F4<>"", E4<>""), F4*E4, "") -> 30 | P4: 3 | Q4: 2.999997 | R4: =IMAGE(W4) | S4: 8400518 - RANUNCULUS - Butterfly - flor ( RANUBUBL, RANUBUSA, 174946, 147132, 126830) | T4: 8400518 | U4: RANUNCULUS - Butterfly - flor | V4: RANUBUBL, RANUBUSA, 174946, 147132, 126830 | W4: https://drive.google.com/uc?export=view&id=1mbmVjM82bGnM8nxdZnDYmJjSQLnHiol0
A5: 1.2 | B5: RANUNCULUS CLOONEY GRAND PASTEL | D5: 1.11 | E5: 6 | F5: 10 | K5: 6 | M5: =IF(E5<>"", E5 - SUM(G5:L5), "") -> 0 | O5: =IF(AND(F5<>"", E5<>""), F5*E5, "") -> 60 | P5: 3 | Q5: 2.999997 | R5: =IMAGE(W5) | S5: 8400518 - RANUNCULUS - Butterfly - flor ( RANUBUBL, RANUBUSA, 174946, 147132, 126830) | T5: 8400518 | U5: RANUNCULUS - Butterfly - flor | V5: RANUBUBL, RANUBUSA, 174946, 147132, 126830 | W5: https://drive.google.com/uc?export=view&id=1mbmVjM82bGnM8nxdZnDYmJjSQLnHiol0
A6: 1.3 | B6: ALSTROEMERIA SI SOFIENA | D6: 0.75 | E6: 6 | F6: 10 | H6: 2 | J6: 2 | K6: 2 | M6: =IF(E6<>"", E6 - SUM(G6:L6), "") -> 0 | O6: =IF(AND(F6<>"", E6<>""), F6*E6, "") -> 60 | Q6: 2.999997 | R6: =IMAGE(W6) | S6: 8400154 - ALSTROEMERIA - flor (00027, 11920, 146548, 148465, ALS VA, 148462, 148466, 11920, ALS-P, 137896, 137077, 137894, 148289, 148469, ALSTROEMERIES ALSTROEMERIA, ALSP, 11920) | T6: 8400154 | U6: ALSTROEMERIA - flor | V6: 00027, 11920, 146548, 148465, ALS VA, 148462, 148466, 11920, ALS-P, 137896, 137077, 137894, 148289, 148469, ALSTROEMERIES ALSTROEMERIA, ALSP, 11920 | W6: https://drive.google.com/uc?export=view&id=1hD_EIkM8w5p_WtnrcMdhYX6szEYoVelf | X6: 0.15
A7: 1.4 | B7: ROSA LARGE BELLE ROSE | D7: 0.58 | E7: 6 | F7: 10 | K7: 6 | M7: =IF(E7<>"", E7 - SUM(G7:L7), "") -> 0 | O7: =IF(AND(F7<>"", E7<>""), F7*E7, "") -> 60 | P7: 2 | Q7: 1.999998 | R7: =IMAGE(W7) | S7: 8400731 - RS ROSA LA BELLE LOLOMARIK - flor (181496) | T7: 8400731 | U7: RS ROSA LA BELLE LOLOMARIK - flor | V7: 181496 | W7: https://drive.google.com/uc?export=view&id=1fUhUDsiSHWrleyP7h5w_2pEpagbWza0G
A8: 1.5 | B8: ROSA GARDEN PRISCILLA! | D8: 0.71 | E8: 6 | F8: 5 | J8: 2 | K8: 4 | M8: =IF(E8<>"", E8 - SUM(G8:L8), "") -> 0 | O8: =IF(AND(F8<>"", E8<>""), F8*E8, "") -> 30 | Q8: 2.999997 | R8: =IMAGE(W8) | S8: 84001081 - ROSA PRISCILLA - flor () | T8: 84001081 | U8: ROSA PRISCILLA - flor | W8: https://drive.google.com/uc?export=view&id=1dI4YSHY8sPn-AzvYOdjKrrjGMV26hEE0
A9: 1.6 | B9: ROSA GARDEN MIX UHURU | D9: 1.19 | E9: 8 | F9: 6 | K9: 8 | M9: =IF(E9<>"", E9 - SUM(G9:L9), "") -> 0 | O9: =IF(AND(F9<>"", E9<>""), F9*E9, "") -> 48 | P9: 3 | S9: 84001157 - RISA GARDAN MIX - flor/3 () | T9: 84001157 | U9: RISA GARDAN MIX - flor/3 | W9: ❗Ошибка: application/json
A10: 1.7 | B10: ROSA SPRAY CHIMO | D10: 0.77 | E10: 8 | F10: 10 | H10: 2 | J10: 3 | K10: 3 | M10: =IF(E10<>"", E10 - SUM(G10:L10), "") -> 0 | O10: =IF(AND(F10<>"", E10<>""), F10*E10, "") -> 80 | Q10: 2.999997 | R10: =IMAGE(W10) | S10: 8400828 - ROSA CHIMO - flor (135409) | T10: 8400828 | U10: ROSA CHIMO - flor | V10: 135409 | W10: https://drive.google.com/uc?export=view&id=14lKbr1IZa_y54C-n_irMTGAXEPdZJoIn
A11: 1.8 | B11: ROSA SPRAY BIRDS NEST+ | D11: 1.52 | E11: 4 | F11: 10 | J11: 1 | K11: 3 | M11: =IF(E11<>"", E11 - SUM(G11:L11), "") -> 0 | O11: =IF(AND(F11<>"", E11<>""), F11*E11, "") -> 40 | P11: 4 | Q11: 3.999996 | R11: =IMAGE(W11) | S11: 84001078 - ROSA BIRDS NEST - flor () | T11: 84001078 | U11: ROSA BIRDS NEST - flor | W11: https://drive.google.com/uc?export=view&id=1cMWmYq9Ijr9CTBLT1xhfRb5ZQ_GrN7hE
A12: 1.9 | B12: ROSA LARGE CELEB | D12: 0.47 | E12: 6 | F12: 10 | H12: 3 | J12: 3 | M12: =IF(E12<>"", E12 - SUM(G12:L12), "") -> 0 | O12: =IF(AND(F12<>"", E12<>""), F12*E12, "") -> 60 | P12: 3 | Q12: 2.999997 | R12: =IMAGE(W12) | S12: 84001044 - ROSA CELEBRATING HEATHER - flor () | T12: 84001044 | U12: ROSA CELEBRATING HEATHER - flor | W12: https://drive.google.com/uc?export=view&id=14z6focMNsmhbYM377L2M-B88nBfvXnJJ
A13: 1.10 | B13: ARR CACTUS | D13: 10.86 | E13: 18 | F13: 1 | J13: 9 | K13: 9 | M13: =IF(E13<>"", E13 - SUM(G13:L13), "") -> 0 | O13: =IF(AND(F13<>"", E13<>""), F13*E13, "") -> 18 | P13: 22 | Q13: 22 | R13: =IMAGE(W13) | S13: 8400594 - CACTUS - planta/22 (TEST 13 cactus) | T13: 8400594 | U13: CACTUS - planta/22 | V13: TEST 13 cactus | W13: https://drive.google.com/uc?export=view&id=1Q-AyZHgyh6uUyL-RDutGOkXSIkuILjHz
A14: 1.11 | B14: ALOE ARBO | D14: 19.07 | E14: 1 | F14: 1 | J14: 1 | M14: =IF(E14<>"", E14 - SUM(G14:L14), "") -> 0 | O14: =IF(AND(F14<>"", E14<>""), F14*E14, "") -> 1 | P14: 67 | Q14: 66.999999 | R14: =IMAGE(W14) | S14: 84001156 - ALOE ARBO - planta/67 () | T14: 84001156 | U14: ALOE ARBO - planta/67 | W14: https://drive.google.com/uc?export=view&id=1nhRiZiSymvZqgrwdzMgNfzK5d8VGqcGQ
A15: 1.12 | B15: ALOE ARBO | D15: 14.53 | E15: 8 | F15: 1 | J15: 4 | K15: 4 | M15: =IF(E15<>"", E15 - SUM(G15:L15), "") -> 0 | O15: =IF(AND(F15<>"", E15<>""), F15*E15, "") -> 8 | P15: 47 | Q15: 46.999997 | R15: =IMAGE(W15) | S15: 84001155 - ALOE ARBO - planta/47 () | T15: 84001155 | U15: ALOE ARBO - planta/47 | W15: https://drive.google.com/uc?export=view&id=1jKGrPrhB6pvkBpjJKJWeb0LNLwFLMWiM
A16: 1.13 | B16: ARR2 MB GROEN IJZER REK 1 BOL | D16: 9.54 | E16: 8 | F16: 1 | J16: 4 | K16: 4 | M16: =IF(E16<>"", E16 - SUM(G16:L16), "") -> 0 | O16: =IF(AND(F16<>"", E16<>""), F16*E16, "") -> 8 | P16: 22 | Q16: 22 | R16: =IMAGE(W16) | S16: 8400410 - SUCCULENTUS T16, T22 - MIX - planta/22 (6CRASA22, 54, CRASS16 ) | T16: 8400410 | U16: SUCCULENTUS T16, T22 - MIX - planta/22 | V16: 6CRASA22, 54, CRASS16 | W16: https://drive.google.com/uc?export=view&id=1NfWhvI4iOJyVFjUEUpFej-EfjH2FiZmQ
A17: 1.14 | B17: ARR NARCISSUS TETE-A-TETE | D17: 5.69 | E17: 12 | F17: 1 | J17: 6 | K17: 6 | M17: =IF(E17<>"", E17 - SUM(G17:L17), "") -> 0 | O17: =IF(AND(F17<>"", E17<>""), F17*E17, "") -> 12 | P17: 14 | Q17: 13.999997 | R17: =IMAGE(W17) | S17: 84001152 - NARCISO TETE-A-TETE - composición/14 () | T17: 84001152 | U17: NARCISO TETE-A-TETE - composición/14 | W17: https://drive.google.com/uc?export=view&id=1jCZc_-4baAz784L3_VmKEcFHD_O4bGxB
A18: 1.15 | B18: ARR NARCISSUS | D18: 6.53 | E18: 8 | F18: 1 | J18: 4 | K18: 4 | M18: =IF(E18<>"", E18 - SUM(G18:L18), "") -> 0 | O18: =IF(AND(F18<>"", E18<>""), F18*E18, "") -> 8 | Q18: 17.000005 | R18: =IMAGE(W18) | S18: 84001038 - NARCIS MASCOTA - planta /17 () | T18: 84001038 | U18: NARCIS MASCOTA - planta /17 | W18: https://drive.google.com/uc?export=view&id=1ANQILzJ7Mt0PRTsFNY6NHq3nJ6aUQJyJ
A19: 1.16 | B19: ARR2 PL KER BAROK DRACENA | D19: 14.37 | E19: 4 | F19: 1 | J19: 4 | M19: =IF(E19<>"", E19 - SUM(G19:L19), "") -> 0 | O19: =IF(AND(F19<>"", E19<>""), F19*E19, "") -> 4 | P19: 38 | Q19: 37.999995 | R19: =IMAGE(W19) | S19: 84001154 - COMPOSITION DE DRECENA - planta/38 () | T19: 84001154 | U19: COMPOSITION DE DRECENA - planta/38 | W19: https://drive.google.com/uc?export=view&id=1Wq_Uard5MdVY8XSrul4hRMbglxiw4tPZ
A20: 1.17 | B20: ARR2 PL KER BAROK DRACENA | D20: 14.37 | E20: 4 | F20: 1 | K20: 4 | M20: =IF(E20<>"", E20 - SUM(G20:L20), "") -> 0 | O20: =IF(AND(F20<>"", E20<>""), F20*E20, "") -> 4 | P20: 38 | Q20: 37.999995 | R20: =IMAGE(W20) | S20: 84001154 - COMPOSITION DE DRECENA - planta/38 () | T20: 84001154 | U20: COMPOSITION DE DRECENA - planta/38 | W20: https://drive.google.com/uc?export=view&id=1rQlNeojmuigxCKDDyLyE9853PtyPfBIF
A21: 1.18 | B21: ARR2 PL GLAS CILINDER PHAL PAARS | D21: 29.24 | E21: 4 | F21: 1 | J21: 2 | K21: 2 | M21: =IF(E21<>"", E21 - SUM(G21:L21), "") -> 0 | O21: =IF(AND(F21<>"", E21<>""), F21*E21, "") -> 4 | P21: 65 | Q21: 65.000001 | R21: =IMAGE(W21) | S21: 84001153 - ARRANGEMENT DE PHALAENOPSIS - composición/56 () | T21: 84001153 | U21: ARRANGEMENT DE PHALAENOPSIS - composición/56 | W21: https://drive.google.com/uc?export=view&id=1SK1jetqpkHm4wysAal2kTf97P1BEWhpF
A22: 1.19 | B22: CRASSULA OVATA | D22: 100.54 | E22: 1 | F22: 1 | J22: 1 | M22: =IF(E22<>"", E22 - SUM(G22:L22), "") -> 0 | O22: =IF(AND(F22<>"", E22<>""), F22*E22, "") -> 1 | P22: 188 | Q22: 188 | R22: =IMAGE(W22) | S22: 8400365 - ARBOL DE JADE T25 -planta/120 ( ARBOL DE JADE GRANDE (Crassula Ovata) T-25) | T22: 8400365 | U22: ARBOL DE JADE T25 -planta/120 | V22: ARBOL DE JADE GRANDE (Crassula Ovata) T-25 | W22: https://drive.google.com/uc?export=view&id=1lx61k_U5Kp0yFS3ThzMZxvaYOsDd3GCE
A23: 1.20 | B23: CRASSULA OVATA | D23: 94.26 | E23: 1 | F23: 1 | K23: 1 | M23: =IF(E23<>"", E23 - SUM(G23:L23), "") -> 0 | O23: =IF(AND(F23<>"", E23<>""), F23*E23, "") -> 1 | P23: 188 | Q23: 188 | R23: =IMAGE(W23) | S23: 8400365 - ARBOL DE JADE T25 -planta/188 ( ARBOL DE JADE GRANDE (Crassula Ovata) T-25) | T23: 8400365 | U23: ARBOL DE JADE T25 -planta/188 | V23: ARBOL DE JADE GRANDE (Crassula Ovata) T-25 | W23: https://drive.google.com/uc?export=view&id=1lx61k_U5Kp0yFS3ThzMZxvaYOsDd3GCE
A24: 1.21 | B24: CODIAEUM VARI MRS ICETON | D24: 23.43 | E24: 3 | F24: 1 | J24: 3 | M24: =IF(E24<>"", E24 - SUM(G24:L24), "") -> 0 | O24: =IF(AND(F24<>"", E24<>""), F24*E24, "") -> 3 | P24: 36 | Q24: 35.999997 | R24: =IMAGE(W24) | S24: 8400558 - CROTON 50cm - Petra - planta/36 (81945, CROMA20) | T24: 8400558 | U24: CROTON 50cm - Petra - planta/36 | V24: 81945, CROMA20 | W24: https://drive.google.com/uc?export=view&id=1bQ_DhntG2uRO8Okt4v1vWc7zG6mHvaCV
A25: 1.22 | B25: LAVANDULA STOE ANOUK | D25: 6.52 | E25: 6 | F25: 1 | K25: 6 | M25: =IF(E25<>"", E25 - SUM(G25:L25), "") -> 0 | O25: =IF(AND(F25<>"", E25<>""), F25*E25, "") -> 6 | Q25: 14.999996 | R25: =IMAGE(W25) | S25: 8400357 - LAVANDULA T13 - planta (LAV13 LAVANDULA T-13, 42454) | T25: 8400357 | U25: LAVANDULA T13 - planta | V25: LAV13 LAVANDULA T-13, 42454 | W25: https://drive.google.com/uc?export=view&id=1b7R1A9LoTC34-OMZMrvcLKwKIECUi_Os
A26: 1.23 | B26: KALANCHOE LUCKY BELLS | D26: 7.27 | E26: 6 | F26: 1 | J26: 6 | M26: =IF(E26<>"", E26 - SUM(G26:L26), "") -> 0 | O26: =IF(AND(F26<>"", E26<>""), F26*E26, "") -> 6 | P26: 18 | Q26: 18.000004 | R26: =IMAGE(W26) | S26: 8400448 - KALANCHOE T25 - Pumila - planta/18 (KAL-P KALANCHOE PUMILA T-25 planta, KCALT) | T26: 8400448 | U26: KALANCHOE T25 - Pumila - planta/18 | V26: KAL-P KALANCHOE PUMILA T-25 planta, KCALT | W26: https://drive.google.com/uc?export=view&id=1OsLbWUraJBcbC_4ErrdcoBAP-oM2MkBa
A27: 1.24 | B27: EUPHORBIA TRIGONA | D27: 4.09 | E27: 10 | F27: 1 | K27: 10 | M27: =IF(E27<>"", E27 - SUM(G27:L27), "") -> 0 | O27: =IF(AND(F27<>"", E27<>""), F27*E27, "") -> 10 | Q27: 22 | R27: =IMAGE(W27) | S27: 8400556 - EUPHORBIA 30cm -Milii - planta/22 (174581, EUV) | T27: 8400556 | U27: EUPHORBIA 30cm -Milii - planta/22 | V27: 174581, EUV | W27: https://drive.google.com/uc?export=view&id=12K7rSNmKuUyPiVea-hixINhAgk9pFzEX
A28: 1.25 | B28: PTPB6537 ARRANGEMENTEN PASEN | D28: 29.75 | E28: 2 | F28: 1 | J28: 1 | K28: 1 | M28: =IF(E28<>"", E28 - SUM(G28:L28), "") -> 0 | O28: =IF(AND(F28<>"", E28<>""), F28*E28, "") -> 2 | P28: 65 | Q28: 65.000001 | R28: =IMAGE(W28) | S28: 84001153 - ARRANGEMENT DE PHALAENOPSIS - composición/56 () | T28: 84001153 | U28: ARRANGEMENT DE PHALAENOPSIS - composición/56 | W28: https://drive.google.com/uc?export=view&id=1SK1jetqpkHm4wysAal2kTf97P1BEWhpF
A29: 1.26 | B29: PTPB6525 ARRANGEMENTEN PASEN | D29: 29.75 | E29: 2 | F29: 1 | J29: 1 | K29: 1 | M29: =IF(E29<>"", E29 - SUM(G29:L29), "") -> 0 | O29: =IF(AND(F29<>"", E29<>""), F29*E29, "") -> 2 | P29: 65 | Q29: 65.000001 | R29: =IMAGE(W29) | S29: 84001153 - ARRANGEMENT DE PHALAENOPSIS - composición/56 () | T29: 84001153 | U29: ARRANGEMENT DE PHALAENOPSIS - composición/56 | W29: https://drive.google.com/uc?export=view&id=1SK1jetqpkHm4wysAal2kTf97P1BEWhpF
A30: 1.27 | B30: PHALAENOPSIS OTHER YELLOW | D30: 15.78 | E30: 6 | F30: 1 | J30: 6 | M30: =IF(E30<>"", E30 - SUM(G30:L30), "") -> 0 | O30: =IF(AND(F30<>"", E30<>""), F30*E30, "") -> 6 | P30: 28 | Q30: 28.000005 | R30: =IMAGE(W30) | S30: 8400391 - PHALAENOPSIS MIX - planta/28 (161202, 179376, 144102, 179304, 191963, 135419, 182797, 127000, 191284) | T30: 8400391 | U30: PHALAENOPSIS MIX - planta/28 | V30: 161202, 179376, 144102, 179304, 191963, 135419, 182797, 127000, 191284 | W30: https://drive.google.com/uc?export=view&id=1r3AGRebywrGIf9rgKm41rhLoFBf_VJYs
A31: 1.28 | B31: SUCCULENTEN OTHER | D31: 10.25 | E31: 3 | F31: 1 | K31: 3 | M31: =IF(E31<>"", E31 - SUM(G31:L31), "") -> 0 | O31: =IF(AND(F31<>"", E31<>""), F31*E31, "") -> 3 | P31: 28 | Q31: 28.000005 | R31: =IMAGE(W31) | S31: 8400591 - SUCCULENTUS OTHER - planta/28 (CRASSCI-9, AEON.012) | T31: 8400591 | U31: SUCCULENTUS OTHER - planta/28 | V31: CRASSCI-9, AEON.012 | W31: https://drive.google.com/uc?export=view&id=1sZGDN8zhyq19KpYdDu_85JCqZfDsrTCK
A32: 1.29 | B32: RHIPSALIS MIX | D32: 4.33 | E32: 24 | F32: 1 | J32: 12 | K32: 12 | M32: =IF(E32<>"", E32 - SUM(G32:L32), "") -> 0 | O32: =IF(AND(F32<>"", E32<>""), F32*E32, "") -> 24 | P32: 12 | Q32: 11.999999 | R32: =IMAGE(W32) | S32: 8400895 - RHIPSALIS MIX - T17 planta colganta (83612) | T32: 8400895 | U32: RHIPSALIS MIX - T17 planta colganta | V32: 83612 | W32: https://drive.google.com/uc?export=view&id=1HMPt7u6wRyq_7yXxw94RmWmhwr-9paUV
M33: =IF(E33<>"", E33 - SUM(G33:L33), "") | O33: =IF(AND(F33<>"", E33<>""), F33*E33, "")
M34: =IF(E34<>"", E34 - SUM(G34:L34), "") | O34: =IF(AND(F34<>"", E34<>""), F34*E34, "")
M35: =IF(E35<>"", E35 - SUM(G35:L35), "") | O35: =IF(AND(F35<>"", E35<>""), F35*E35, "")
M36: =IF(E36<>"", E36 - SUM(G36:L36), "") | O36: =IF(AND(F36<>"", E36<>""), F36*E36, "")
M37: =IF(E37<>"", E37 - SUM(G37:L37), "") | O37: =IF(AND(F37<>"", E37<>""), F37*E37, "")
M38: =IF(E38<>"", E38 - SUM(G38:L38), "") | O38: =IF(AND(F38<>"", E38<>""), F38*E38, "")
M39: =IF(E39<>"", E39 - SUM(G39:L39), "") | O39: =IF(AND(F39<>"", E39<>""), F39*E39, "")
M40: =IF(E40<>"", E40 - SUM(G40:L40), "") | O40: =IF(AND(F40<>"", E40<>""), F40*E40, "")
M41: =IF(E41<>"", E41 - SUM(G41:L41), "") | O41: =IF(AND(F41<>"", E41<>""), F41*E41, "")
M43: =IF(E43<>"", E43 - SUM(G43:L43), "") | O43: =IF(AND(F43<>"", E43<>""), F43*E43, "")
M44: =IF(E44<>"", E44 - SUM(G44:L44), "") | O44: =IF(AND(F44<>"", E44<>""), F44*E44, "")
M45: =IF(E45<>"", E45 - SUM(G45:L45), "") | O45: =IF(AND(F45<>"", E45<>""), F45*E45, "")
... M196: =IF(E196<>"", E196 - SUM(G196:L196), "") | O196: =IF(AND(F196<>"", E196<>""), F196*E196, "")

Sheet Muntaner
A1: M | B1: =VLOOKUP(A1, Lookup!B:C, 2, FALSE) -> Muntaner | D1: послали пачек | E1: ='Закупка'!F1 -> внтури пачки штук? | F1: послали штук товара | G1: ИМЯ флориста написать | J1: расхождение
A2: =MATCH(A1, 'Закупка'!G1:K1, 0) -> 1 | B2: ='Закупка'!B2 -> 45845 | G2: приехало пачек | H2: реально штук товара | I2: коментарий | K2: ='Закупка'!T1 -> Holded артикул | L2: ='Закупка'!U1 -> название с holded | M2: ='Закупка'!V1 -> codigo de fabricasion
A3: ='Закупка'!A3 | B3: ='Закупка'!B3 -> Фактура 1 | C3: ='Закупка'!R3 | D3: {=INDEX('Закупка'!G3:K3, $A$2)} | E3: ='Закупка'!F3 | F3: =IF(D3<>"",D3*E3,) | K3: ='Закупка'!T3 | L3: ='Закупка'!U3 | M3: ='Закупка'!V3
A4: ='Закупка'!A4 -> 1.1 | B4: ='Закупка'!B4 -> RANUNCULUS CLOONEY TUAREQ | C4: ='Закупка'!R4 | D4: {=INDEX('Закупка'!G4:K4, $A$2)} | E4: ='Закупка'!F4 -> 10 | F4: =IF(D4<>"",D4*E4,) | K4: ='Закупка'!T4 -> 8400518 | L4: ='Закупка'!U4 -> RANUNCULUS - Butterfly - flor | M4: ='Закупка'!V4 -> RANUBUBL, RANUBUSA, 174946, 147132, 126830
A5: ='Закупка'!A5 -> 1.2 | B5: ='Закупка'!B5 -> RANUNCULUS CLOONEY GRAND PASTEL | C5: ='Закупка'!R5 | D5: {=INDEX('Закупка'!G5:K5, $A$2)} | E5: ='Закупка'!F5 -> 10 | F5: =IF(D5<>"",D5*E5,) | K5: ='Закупка'!T5 -> 8400518 | L5: ='Закупка'!U5 -> RANUNCULUS - Butterfly - flor | M5: ='Закупка'!V5 -> RANUBUBL, RANUBUSA, 174946, 147132, 126830
A6: ='Закупка'!A6 -> 1.3 | B6: ='Закупка'!B6 -> ALSTROEMERIA SI SOFIENA | C6: ='Закупка'!R6 | D6: {=INDEX('Закупка'!G6:K6, $A$2)} | E6: ='Закупка'!F6 -> 10 | F6: =IF(D6<>"",D6*E6,) | K6: ='Закупка'!T6 -> 8400154 | L6: ='Закупка'!U6 -> ALSTROEMERIA - flor | M6: ='Закупка'!V6 -> 00027, 11920, 146548, 148465, ALS VA, 148462, 148466, 11920, ALS-P, 137896, 137077, 137894, 148289, 148469, ALSTROEMERIES ALSTROEMERIA, ALSP, 11920
A7: ='Закупка'!A7 -> 1.4 | B7: ='Закупка'!B7 -> ROSA LARGE BELLE ROSE | C7: ='Закупка'!R7 | D7: {=INDEX('Закупка'!G7:K7, $A$2)} | E7: ='Закупка'!F7 -> 10 | F7: =IF(D7<>"",D7*E7,) | K7: ='Закупка'!T7 -> 8400731 | L7: ='Закупка'!U7 -> RS ROSA LA BELLE LOLOMARIK - flor | M7: ='Закупка'!V7 -> 181496
A8: ='Закупка'!A8 -> 1.5 | B8: ='Закупка'!B8 -> ROSA GARDEN PRISCILLA! | C8: ='Закупка'!R8 | D8: {=INDEX('Закупка'!G8:K8, $A$2)} | E8: ='Закупка'!F8 -> 5 | F8: =IF(D8<>"",D8*E8,) | K8: ='Закупка'!T8 -> 84001081 | L8: ='Закупка'!U8 -> ROSA PRISCILLA - flor | M8: ='Закупка'!V8
A9: ='Закупка'!A9 -> 1.6 | B9: ='Закупка'!B9 -> ROSA GARDEN MIX UHURU | C9: ='Закупка'!R9 | D9: {=INDEX('Закупка'!G9:K9, $A$2)} | E9: ='Закупка'!F9 -> 6 | F9: =IF(D9<>"",D9*E9,) | K9: ='Закупка'!T9 -> 84001157 | L9: ='Закупка'!U9 -> RISA GARDAN MIX - flor/3 | M9: ='Закупка'!V9
A10: ='Закупка'!A10 -> 1.7 | B10: ='Закупка'!B10 -> ROSA SPRAY CHIMO | C10: ='Закупка'!R10 | D10: {=INDEX('Закупка'!G10:K10, $A$2)} | E10: ='Закупка'!F10 -> 10 | F10: =IF(D10<>"",D10*E10,) | K10: ='Закупка'!T10 -> 8400828 | L10: ='Закупка'!U10 -> ROSA CHIMO - flor | M10: ='Закупка'!V10 -> 135409
A11: ='Закупка'!A11 -> 1.8 | B11: ='Закупка'!B11 -> ROSA SPRAY BIRDS NEST+ | C11: ='Закупка'!R11 | D11: {=INDEX('Закупка'!G11:K11, $A$2)} | E11: ='Закупка'!F11 -> 10 | F11: =IF(D11<>"",D11*E11,) | K11: ='Закупка'!T11 -> 84001078 | L11: ='Закупка'!U11 -> ROSA BIRDS NEST - flor | M11: ='Закупка'!V11
A12: ='Закупка'!A12 -> 1.9 | B12: ='Закупка'!B12 -> ROSA LARGE CELEB | C12: ='Закупка'!R12 | D12: {=INDEX('Закупка'!G12:K12, $A$2)} | E12: ='Закупка'!F12 -> 10 | F12: =IF(D12<>"",D12*E12,) | K12: ='Закупка'!T12 -> 84001044 | L12: ='Закупка'!U12 -> ROSA CELEBRATING HEATHER - flor | M12: ='Закупка'!V12
A13: ='Закупка'!A13 -> 1.10 | B13: ='Закупка'!B13 -> ARR CACTUS | C13: ='Закупка'!R13 | D13: {=INDEX('Закупка'!G13:K13, $A$2)} | E13: ='Закупка'!F13 -> 1 | F13: =IF(D13<>"",D13*E13,) | K13: ='Закупка'!T13 -> 8400594 | L13: ='Закупка'!U13 -> CACTUS - planta/22 | M13: ='Закупка'!V13 -> TEST 13 cactus
A14: ='Закупка'!A14 -> 1.11 | B14: ='Закупка'!B14 -> ALOE ARBO | C14: ='Закупка'!R14 | D14: {=INDEX('Закупка'!G14:K14, $A$2)} | E14: ='Закупка'!F14 -> 1 | F14: =IF(D14<>"",D14*E14,) | K14: ='Закупка'!T14 -> 84001156 | L14: ='Закупка'!U14 -> ALOE ARBO - planta/67 | M14: ='Закупка'!V14
... A97: ='Закупка'!A97 | B97: ='Закупка'!B97 | C97: ='Закупка'!R97 | D97: {=INDEX('Закупка'!G97:K97, $A$2)} | E97: ='Закупка'!F97 | F97: =IF(D97<>"",D97*E97,) | K97: ='Закупка'!T97 | L97: ='Закупка'!U97 | M97: ='Закупка'!V97
A98: ='Закупка'!A98 | B98: ='Закупка'!B98 | C98: ='Закупка'!R98 | D98: {=INDEX('Закупка'!G98:K98, $A$2)} | E98: ='Закупка'!F98 | F98: =IF(D98<>"",D98*E98,) | J98: =IF(H98<>"", H98-F98,) | K98: ='Закупка'!T98 | L98: ='Закупка'!U98 | M98: ='Закупка'!V98
A99: ='Закупка'!A99 | B99: ='Закупка'!B99 | C99: ='Закупка'!R99 | D99: {=INDEX('Закупка'!G99:K99, $A$2)} | E99: ='Закупка'!F99 | F99: =IF(D99<>"",D99*E99,) | J99: =IF(H99<>"", H99-F99,) | K99: ='Закупка'!T99 | L99: ='Закупка'!U99 | M99: ='Закупка'!V99
A100: ='Закупка'!A100 | B100: ='Закупка'!B100 | C100: ='Закупка'!R100 | D100: {=INDEX('Закупка'!G100:K100, $A$2)} | E100: ='Закупка'!F100 | F100: =IF(D100<>"",D100*E100,) | J100: =IF(H100<>"", H100-F100,) | K100: ='Закупка'!T100 | L100: ='Закупка'!U100 | M100: ='Закупка'!V100
A101: ='Закупка'!A101 | B101: ='Закупка'!B101 | C101: ='Закупка'!R101 | D101: {=INDEX('Закупка'!G101:K101, $A$2)} | E101: ='Закупка'!F101 | F101: =IF(D101<>"",D101*E101,) | J101: =IF(H101<>"", H101-F101,) | K101: ='Закупка'!T101 | L101: ='Закупка'!U101 | M101: ='Закупка'!V101
A102: ='Закупка'!A102 | B102: ='Закупка'!B102 | C102: ='Закупка'!R102 | D102: {=INDEX('Закупка'!G102:K102, $A$2)} | E102: ='Закупка'!F102 | F102: =IF(D102<>"",D102*E102,) | J102: =IF(H102<>"", H102-F102,) | K102: ='Закупка'!T102 | L102: ='Закупка'!U102 | M102: ='Закупка'!V102
A103: ='Закупка'!A103 | B103: ='Закупка'!B103 | C103: ='Закупка'!R103 | D103: {=INDEX('Закупка'!G103:K103, $A$2)} | E103: ='Закупка'!F103 | F103: =IF(D103<>"",D103*E103,) | J103: =IF(H103<>"", H103-F103,) | K103: ='Закупка'!T103 | L103: ='Закупка'!U103 | M103: ='Закупка'!V103
A104: ='Закупка'!A104 | B104: ='Закупка'!B104 | C104: ='Закупка'!R104 | D104: {=INDEX('Закупка'!G104:K104, $A$2)} | E104: ='Закупка'!F104 | F104: =IF(D104<>"",D104*E104,) | J104: =IF(H104<>"", H104-F104,) | K104: ='Закупка'!T104 | L104: ='Закупка'!U104 | M104: ='Закупка'!V104
A105: ='Закупка'!A105 | B105: ='Закупка'!B105 | C105: ='Закупка'!R105 | D105: {=INDEX('Закупка'!G105:K105, $A$2)} | E105: ='Закупка'!F105 | F105: =IF(D105<>"",D105*E105,) | J105: =IF(H105<>"", H105-F105,) | K105: ='Закупка'!T105 | L105: ='Закупка'!U105 | M105: ='Закупка'!V105
A106: ='Закупка'!A106 | B106: ='Закупка'!B106 | C106: ='Закупка'!R106 | D106: {=INDEX('Закупка'!G106:K106, $A$2)} | E106: ='Закупка'!F106 | F106: =IF(D106<>"",D106*E106,) | J106: =IF(H106<>"", H106-F106,) | K106: ='Закупка'!T106 | L106: ='Закупка'!U106 | M106: ='Закупка'!V106
A107: ='Закупка'!A107 | B107: ='Закупка'!B107 | C107: ='Закупка'!R107 | D107: {=INDEX('Закупка'!G107:K107, $A$2)} | E107: ='Закупка'!F107 | F107: =IF(D107<>"",D107*E107,) | J107: =IF(H107<>"", H107-F107,) | K107: ='Закупка'!T107 | L107: ='Закупка'!U107 | M107: ='Закупка'!V107
A108: ='Закупка'!A108 | B108: ='Закупка'!B108 | C108: ='Закупка'!R108 | D108: {=INDEX('Закупка'!G108:K108, $A$2)} | E108: ='Закупка'!F108 | F108: =IF(D108<>"",D108*E108,) | J108: =IF(H108<>"", H108-F108,) | K108: ='Закупка'!T108 | L108: ='Закупка'!U108 | M108: ='Закупка'!V108
A109: ='Закупка'!A109 | B109: ='Закупка'!B109 | C109: ='Закупка'!R109 | D109: {=INDEX('Закупка'!G109:K109, $A$2)} | E109: ='Закупка'!F109 | F109: =IF(D109<>"",D109*E109,) | J109: =IF(H109<>"", H109-F109,) | K109: ='Закупка'!T109 | L109: ='Закупка'!U109 | M109: ='Закупка'!V109
... A199: ='Закупка'!A199 | B199: ='Закупка'!B199 | C199: ='Закупка'!R199 | D199: {=INDEX('Закупка'!G199:K199, $A$2)} | E199: ='Закупка'!F199 | F199: =IF(D199<>"",D199*E199,) | J199: =IF(H199<>"", H199-F199,) | K199: ='Закупка'!T199 | L199: ='Закупка'!U199 | M199: ='Закупка'!V199

Sheet Plaza
A1: P | B1: =VLOOKUP(A1, Lookup!B:C, 2, FALSE) -> Plaza | D1: послали пачек | E1: ='Закупка'!F1 -> внтури пачки штук? | F1: послали штук товара | G1: ИМЯ флориста написать | J1: расхождение
A2: =MATCH(A1, 'Закупка'!G1:K1, 0) -> 2 | B2: ='Закупка'!B2 -> 45845 | G2: приехало пачек | H2: реально штук товара | I2: коментарий | K2: ='Закупка'!T1 -> Holded артикул | L2: ='Закупка'!U1 -> название с holded | M2: ='Закупка'!V1 -> codigo de fabricasion
A3: ='Закупка'!A3 | B3: ='Закупка'!B3 -> Фактура 1 | C3: ='Закупка'!R3 | D3: {=INDEX('Закупка'!G3:K3, $A$2)} | E3: ='Закупка'!F3 | F3: =IF(D3<>"",D3*E3,) | K3: ='Закупка'!T3 | L3: ='Закупка'!U3 | M3: ='Закупка'!V3
A4: ='Закупка'!A4 -> 1.1 | B4: ='Закупка'!B4 -> RANUNCULUS CLOONEY TUAREQ | C4: ='Закупка'!R4 | D4: {=INDEX('Закупка'!G4:K4, $A$2)} | E4: ='Закупка'!F4 -> 10 | F4: =IF(D4<>"",D4*E4,) | K4: ='Закупка'!T4 -> 8400518 | L4: ='Закупка'!U4 -> RANUNCULUS - Butterfly - flor | M4: ='Закупка'!V4 -> RANUBUBL, RANUBUSA, 174946, 147132, 126830
A5: ='Закупка'!A5 -> 1.2 | B5: ='Закупка'!B5 -> RANUNCULUS CLOONEY GRAND PASTEL | C5: ='Закупка'!R5 | D5: {=INDEX('Закупка'!G5:K5, $A$2)} | E5: ='Закупка'!F5 -> 10 | F5: =IF(D5<>"",D5*E5,) | K5: ='Закупка'!T5 -> 8400518 | L5: ='Закупка'!U5 -> RANUNCULUS - Butterfly - flor | M5: ='Закупка'!V5 -> RANUBUBL, RANUBUSA, 174946, 147132, 126830
A6: ='Закупка'!A6 -> 1.3 | B6: ='Закупка'!B6 -> ALSTROEMERIA SI SOFIENA | C6: ='Закупка'!R6 | D6: {=INDEX('Закупка'!G6:K6, $A$2)} -> 2 | E6: ='Закупка'!F6 -> 10 | F6: =IF(D6<>"",D6*E6,) -> 20 | G6: 2 | H6: 20 | K6: ='Закупка'!T6 -> 8400154 | L6: ='Закупка'!U6 -> ALSTROEMERIA - flor | M6: ='Закупка'!V6 -> 00027, 11920, 146548, 148465, ALS VA, 148462, 148466, 11920, ALS-P, 137896, 137077, 137894, 148289, 148469, ALSTROEMERIES ALSTROEMERIA, ALSP, 11920
A7: ='Закупка'!A7 -> 1.4 | B7: ='Закупка'!B7 -> ROSA LARGE BELLE ROSE | C7: ='Закупка'!R7 | D7: {=INDEX('Закупка'!G7:K7, $A$2)} | E7: ='Закупка'!F7 -> 10 | F7: =IF(D7<>"",D7*E7,) | K7: ='Закупка'!T7 -> 8400731 | L7: ='Закупка'!U7 -> RS ROSA LA BELLE LOLOMARIK - flor | M7: ='Закупка'!V7 -> 181496
A8: ='Закупка'!A8 -> 1.5 | B8: ='Закупка'!B8 -> ROSA GARDEN PRISCILLA! | C8: ='Закупка'!R8 | D8: {=INDEX('Закупка'!G8:K8, $A$2)} | E8: ='Закупка'!F8 -> 5 | F8: =IF(D8<>"",D8*E8,) | K8: ='Закупка'!T8 -> 84001081 | L8: ='Закупка'!U8 -> ROSA PRISCILLA - flor | M8: ='Закупка'!V8
A9: ='Закупка'!A9 -> 1.6 | B9: ='Закупка'!B9 -> ROSA GARDEN MIX UHURU | C9: ='Закупка'!R9 | D9: {=INDEX('Закупка'!G9:K9, $A$2)} | E9: ='Закупка'!F9 -> 6 | F9: =IF(D9<>"",D9*E9,) | K9: ='Закупка'!T9 -> 84001157 | L9: ='Закупка'!U9 -> RISA GARDAN MIX - flor/3 | M9: ='Закупка'!V9
A10: ='Закупка'!A10 -> 1.7 | B10: ='Закупка'!B10 -> ROSA SPRAY CHIMO | C10: ='Закупка'!R10 | D10: {=INDEX('Закупка'!G10:K10, $A$2)} -> 2 | E10: ='Закупка'!F10 -> 10 | F10: =IF(D10<>"",D10*E10,) -> 20 | G10: 2 | H10: 20 | K10: ='Закупка'!T10 -> 8400828 | L10: ='Закупка'!U10 -> ROSA CHIMO - flor | M10: ='Закупка'!V10 -> 135409
A11: ='Закупка'!A11 -> 1.8 | B11: ='Закупка'!B11 -> ROSA SPRAY BIRDS NEST+ | C11: ='Закупка'!R11 | D11: {=INDEX('Закупка'!G11:K11, $A$2)} | E11: ='Закупка'!F11 -> 10 | F11: =IF(D11<>"",D11*E11,) | K11: ='Закупка'!T11 -> 84001078 | L11: ='Закупка'!U11 -> ROSA BIRDS NEST - flor | M11: ='Закупка'!V11
A12: ='Закупка'!A12 -> 1.9 | B12: ='Закупка'!B12 -> ROSA LARGE CELEB | C12: ='Закупка'!R12 | D12: {=INDEX('Закупка'!G12:K12, $A$2)} -> 3 | E12: ='Закупка'!F12 -> 10 | F12: =IF(D12<>"",D12*E12,) -> 30 | G12: 3 | H12: 30 | K12: ='Закупка'!T12 -> 84001044 | L12: ='Закупка'!U12 -> ROSA CELEBRATING HEATHER - flor | M12: ='Закупка'!V12
A13: ='Закупка'!A13 -> 1.10 | B13: ='Закупка'!B13 -> ARR CACTUS | C13: ='Закупка'!R13 | D13: {=INDEX('Закупка'!G13:K13, $A$2)} | E13: ='Закупка'!F13 -> 1 | F13: =IF(D13<>"",D13*E13,) | K13: ='Закупка'!T13 -> 8400594 | L13: ='Закупка'!U13 -> CACTUS - planta/22 | M13: ='Закупка'!V13 -> TEST 13 cactus
A14: ='Закупка'!A14 -> 1.11 | B14: ='Закупка'!B14 -> ALOE ARBO | C14: ='Закупка'!R14 | D14: {=INDEX('Закупка'!G14:K14, $A$2)} | E14: ='Закупка'!F14 -> 1 | F14: =IF(D14<>"",D14*E14,) | K14: ='Закупка'!T14 -> 84001156 | L14: ='Закупка'!U14 -> ALOE ARBO - planta/67 | M14: ='Закупка'!V14
A15: ='Закупка'!A15 -> 1.12 | B15: ='Закупка'!B15 -> ALOE ARBO | C15: ='Закупка'!R15 | D15: {=INDEX('Закупка'!G15:K15, $A$2)} | E15: ='Закупка'!F15 -> 1 | F15: =IF(D15<>"",D15*E15,) | K15: ='Закупка'!T15 -> 84001155 | L15: ='Закупка'!U15 -> ALOE ARBO - planta/47 | M15: ='Закупка'!V15
A16: ='Закупка'!A16 -> 1.13 | B16: ='Закупка'!B16 -> ARR2 MB GROEN IJZER REK 1 BOL | C16: ='Закупка'!R16 | D16: {=INDEX('Закупка'!G16:K16, $A$2)} | E16: ='Закупка'!F16 -> 1 | F16: =IF(D16<>"",D16*E16,) | K16: ='Закупка'!T16 -> 8400410 | L16: ='Закупка'!U16 -> SUCCULENTUS T16, T22 - MIX - planta/22 | M16: ='Закупка'!V16 -> 6CRASA22, 54, CRASS16
A17: ='Закупка'!A17 -> 1.14 | B17: ='Закупка'!B17 -> ARR NARCISSUS TETE-A-TETE | C17: ='Закупка'!R17 | D17: {=INDEX('Закупка'!G17:K17, $A$2)} | E17: ='Закупка'!F17 -> 1 | F17: =IF(D17<>"",D17*E17,) | K17: ='Закупка'!T17 -> 84001152 | L17: ='Закупка'!U17 -> NARCISO TETE-A-TETE - composición/14 | M17: ='Закупка'!V17
A18: ='Закупка'!A18 -> 1.15 | B18: ='Закупка'!B18 -> ARR NARCISSUS | C18: ='Закупка'!R18 | D18: {=INDEX('Закупка'!G18:K18, $A$2)} | E18: ='Закупка'!F18 -> 1 | F18: =IF(D18<>"",D18*E18,) | K18: ='Закупка'!T18 -> 84001038 | L18: ='Закупка'!U18 -> NARCIS MASCOTA - planta /17 | M18: ='Закупка'!V18
A19: ='Закупка'!A19 -> 1.16 | B19: ='Закупка'!B19 -> ARR2 PL KER BAROK DRACENA | C19: ='Закупка'!R19 | D19: {=INDEX('Закупка'!G19:K19, $A$2)} | E19: ='Закупка'!F19 -> 1 | F19: =IF(D19<>"",D19*E19,) | K19: ='Закупка'!T19 -> 84001154 | L19: ='Закупка'!U19 -> COMPOSITION DE DRECENA - planta/38 | M19: ='Закупка'!V19
A20: ='Закупка'!A20 -> 1.17 | B20: ='Закупка'!B20 -> ARR2 PL KER BAROK DRACENA | C20: ='Закупка'!R20 | D20: {=INDEX('Закупка'!G20:K20, $A$2)} | E20: ='Закупка'!F20 -> 1 | F20: =IF(D20<>"",D20*E20,) | K20: ='Закупка'!T20 -> 84001154 | L20: ='Закупка'!U20 -> COMPOSITION DE DRECENA - planta/38 | M20: ='Закупка'!V20
A21: ='Закупка'!A21 -> 1.18 | B21: ='Закупка'!B21 -> ARR2 PL GLAS CILINDER PHAL PAARS | C21: ='Закупка'!R21 | D21: {=INDEX('Закупка'!G21:K21, $A$2)} | E21: ='Закупка'!F21 -> 1 | F21: =IF(D21<>"",D21*E21,) | K21: ='Закупка'!T21 -> 84001153 | L21: ='Закупка'!U21 -> ARRANGEMENT DE PHALAENOPSIS - composición/56 | M21: ='Закупка'!V21
A22: ='Закупка'!A22 -> 1.19 | B22: ='Закупка'!B22 -> CRASSULA OVATA | C22: ='Закупка'!R22 | D22: {=INDEX('Закупка'!G22:K22, $A$2)} | E22: ='Закупка'!F22 -> 1 | F22: =IF(D22<>"",D22*E22,) | K22: ='Закупка'!T22 -> 8400365 | L22: ='Закупка'!U22 -> ARBOL DE JADE T25 -planta/120 | M22: ='Закупка'!V22 -> ARBOL DE JADE GRANDE (Crassula Ovata) T-25
A23: ='Закупка'!A23 -> 1.20 | B23: ='Закупка'!B23 -> CRASSULA OVATA | C23: ='Закупка'!R23 | D23: {=INDEX('Закупка'!G23:K23, $A$2)} | E23: ='Закупка'!F23 -> 1 | F23: =IF(D23<>"",D23*E23,) | K23: ='Закупка'!T23 -> 8400365 | L23: ='Закупка'!U23 -> ARBOL DE JADE T25 -planta/188 | M23: ='Закупка'!V23 -> ARBOL DE JADE GRANDE (Crassula Ovata) T-25
A24: ='Закупка'!A24 -> 1.21 | B24: ='Закупка'!B24 -> CODIAEUM VARI MRS ICETON | C24: ='Закупка'!R24 | D24: {=INDEX('Закупка'!G24:K24, $A$2)} | E24: ='Закупка'!F24 -> 1 | F24: =IF(D24<>"",D24*E24,) | K24: ='Закупка'!T24 -> 8400558 | L24: ='Закупка'!U24 -> CROTON 50cm - Petra - planta/36 | M24: ='Закупка'!V24 -> 81945, CROMA20
... A100: ='Закупка'!A100 | B100: ='Закупка'!B100 | C100: ='Закупка'!R100 | D100: {=INDEX('Закупка'!G100:K100, $A$2)} | E100: ='Закупка'!F100 | F100: =IF(D100<>"",D100*E100,) | K100: ='Закупка'!T100 | L100: ='Закупка'!U100 | M100: ='Закупка'!V100
A101: ='Закупка'!A101 | B101: ='Закупка'!B101 | C101: ='Закупка'!R101 | D101: {=INDEX('Закупка'!G101:K101, $A$2)} | E101: ='Закупка'!F101 | F101: =IF(D101<>"",D101*E101,) | J101: =IF(H101<>"", H101-F101,) | K101: ='Закупка'!T101 | L101: ='Закупка'!U101 | M101: ='Закупка'!V101
A102: ='Закупка'!A102 | B102: ='Закупка'!B102 | C102: ='Закупка'!R102 | D102: {=INDEX('Закупка'!G102:K102, $A$2)} | E102: ='Закупка'!F102 | F102: =IF(D102<>"",D102*E102,) | J102: =IF(H102<>"", H102-F102,) | K102: ='Закупка'!T102 | L102: ='Закупка'!U102 | M102: ='Закупка'!V102
A103: ='Закупка'!A103 | B103: ='Закупка'!B103 | C103: ='Закупка'!R103 | D103: {=INDEX('Закупка'!G103:K103, $A$2)} | E103: ='Закупка'!F103 | F103: =IF(D103<>"",D103*E103,) | J103: =IF(H103<>"", H103-F103,) | K103: ='Закупка'!T103 | L103: ='Закупка'!U103 | M103: ='Закупка'!V103
A104: ='Закупка'!A104 | B104: ='Закупка'!B104 | C104: ='Закупка'!R104 | D104: {=INDEX('Закупка'!G104:K104, $A$2)} | E104: ='Закупка'!F104 | F104: =IF(D104<>"",D104*E104,) | J104: =IF(H104<>"", H104-F104,) | K104: ='Закупка'!T104 | L104: ='Закупка'!U104 | M104: ='Закупка'!V104
A105: ='Закупка'!A105 | B105: ='Закупка'!B105 | C105: ='Закупка'!R105 | D105: {=INDEX('Закупка'!G105:K105, $A$2)} | E105: ='Закупка'!F105 | F105: =IF(D105<>"",D105*E105,) | J105: =IF(H105<>"", H105-F105,) | K105: ='Закупка'!T105 | L105: ='Закупка'!U105 | M105: ='Закупка'!V105
A106: ='Закупка'!A106 | B106: ='Закупка'!B106 | C106: ='Закупка'!R106 | D106: {=INDEX('Закупка'!G106:K106, $A$2)} | E106: ='Закупка'!F106 | F106: =IF(D106<>"",D106*E106,) | J106: =IF(H106<>"", H106-F106,) | K106: ='Закупка'!T106 | L106: ='Закупка'!U106 | M106: ='Закупка'!V106
A107: ='Закупка'!A107 | B107: ='Закупка'!B107 | C107: ='Закупка'!R107 | D107: {=INDEX('Закупка'!G107:K107, $A$2)} | E107: ='Закупка'!F107 | F107: =IF(D107<>"",D107*E107,) | J107: =IF(H107<>"", H107-F107,) | K107: ='Закупка'!T107 | L107: ='Закупка'!U107 | M107: ='Закупка'!V107
A108: ='Закупка'!A108 | B108: ='Закупка'!B108 | C108: ='Закупка'!R108 | D108: {=INDEX('Закупка'!G108:K108, $A$2)} | E108: ='Закупка'!F108 | F108: =IF(D108<>"",D108*E108,) | J108: =IF(H108<>"", H108-F108,) | K108: ='Закупка'!T108 | L108: ='Закупка'!U108 | M108: ='Закупка'!V108
A109: ='Закупка'!A109 | B109: ='Закупка'!B109 | C109: ='Закупка'!R109 | D109: {=INDEX('Закупка'!G109:K109, $A$2)} | E109: ='Закупка'!F109 | F109: =IF(D109<>"",D109*E109,) | J109: =IF(H109<>"", H109-F109,) | K109: ='Закупка'!T109 | L109: ='Закупка'!U109 | M109: ='Закупка'!V109
A110: ='Закупка'!A110 | B110: ='Закупка'!B110 | C110: ='Закупка'!R110 | D110: {=INDEX('Закупка'!G110:K110, $A$2)} | E110: ='Закупка'!F110 | F110: =IF(D110<>"",D110*E110,) | J110: =IF(H110<>"", H110-F110,) | K110: ='Закупка'!T110 | L110: ='Закупка'!U110 | M110: ='Закупка'!V110
A111: ='Закупка'!A111 | B111: ='Закупка'!B111 | C111: ='Закупка'!R111 | D111: {=INDEX('Закупка'!G111:K111, $A$2)} | E111: ='Закупка'!F111 | F111: =IF(D111<>"",D111*E111,) | J111: =IF(H111<>"", H111-F111,) | K111: ='Закупка'!T111 | L111: ='Закупка'!U111 | M111: ='Закупка'!V111
A112: ='Закупка'!A112 | B112: ='Закупка'!B112 | C112: ='Закупка'!R112 | D112: {=INDEX('Закупка'!G112:K112, $A$2)} | E112: ='Закупка'!F112 | F112: =IF(D112<>"",D112*E112,) | J112: =IF(H112<>"", H112-F112,) | K112: ='Закупка'!T112 | L112: ='Закупка'!U112 | M112: ='Закупка'!V112
... A199: ='Закупка'!A199 | B199: ='Закупка'!B199 | C199: ='Закупка'!R199 | D199: {=INDEX('Закупка'!G199:K199, $A$2)} | E199: ='Закупка'!F199 | F199: =IF(D199<>"",D199*E199,) | J199: =IF(H199<>"", H199-F199,) | K199: ='Закупка'!T199 | L199: ='Закупка'!U199 | M199: ='Закупка'!V199

Sheet Augusta
A1: A | B1: =VLOOKUP(A1, Lookup!B:C, 2, FALSE) -> Augusta | D1: послали пачек | E1: ='Закупка'!F1 -> внтури пачки штук? | F1: послали штук товара | G1: ИМЯ флориста написать | J1: расхождение
A2: =MATCH(A1, 'Закупка'!G1:K1, 0) -> 3 | B2: ='Закупка'!B2 -> 45845 | G2: приехало пачек | H2: реально штук товара | I2: коментарий | K2: ='Закупка'!T1 -> Holded артикул | L2: ='Закупка'!U1 -> название с holded | M2: ='Закупка'!V1 -> codigo de fabricasion
A3: ='Закупка'!A3 | B3: ='Закупка'!B3 -> Фактура 1 | C3: ='Закупка'!R3 | D3: {=INDEX('Закупка'!G3:K3, $A$2)} | E3: ='Закупка'!F3 | F3: =IF(D3<>"",D3*E3,) | K3: ='Закупка'!T3 | L3: ='Закупка'!U3 | M3: ='Закупка'!V3
A4: ='Закупка'!A4 -> 1.1 | B4: ='Закупка'!B4 -> RANUNCULUS CLOONEY TUAREQ | C4: ='Закупка'!R4 | D4: {=INDEX('Закупка'!G4:K4, $A$2)} | E4: ='Закупка'!F4 -> 10 | F4: =IF(D4<>"",D4*E4,) | K4: ='Закупка'!T4 -> 8400518 | L4: ='Закупка'!U4 -> RANUNCULUS - Butterfly - flor | M4: ='Закупка'!V4 -> RANUBUBL, RANUBUSA, 174946, 147132, 126830
A5: ='Закупка'!A5 -> 1.2 | B5: ='Закупка'!B5 -> RANUNCULUS CLOONEY GRAND PASTEL | C5: ='Закупка'!R5 | D5: {=INDEX('Закупка'!G5:K5, $A$2)} | E5: ='Закупка'!F5 -> 10 | F5: =IF(D5<>"",D5*E5,) | K5: ='Закупка'!T5 -> 8400518 | L5: ='Закупка'!U5 -> RANUNCULUS - Butterfly - flor | M5: ='Закупка'!V5 -> RANUBUBL, RANUBUSA, 174946, 147132, 126830
A6: ='Закупка'!A6 -> 1.3 | B6: ='Закупка'!B6 -> ALSTROEMERIA SI SOFIENA | C6: ='Закупка'!R6 | D6: {=INDEX('Закупка'!G6:K6, $A$2)} | E6: ='Закупка'!F6 -> 10 | F6: =IF(D6<>"",D6*E6,) | K6: ='Закупка'!T6 -> 8400154 | L6: ='Закупка'!U6 -> ALSTROEMERIA - flor | M6: ='Закупка'!V6 -> 00027, 11920, 146548, 148465, ALS VA, 148462, 148466, 11920, ALS-P, 137896, 137077, 137894, 148289, 148469, ALSTROEMERIES ALSTROEMERIA, ALSP, 11920
A7: ='Закупка'!A7 -> 1.4 | B7: ='Закупка'!B7 -> ROSA LARGE BELLE ROSE | C7: ='Закупка'!R7 | D7: {=INDEX('Закупка'!G7:K7, $A$2)} | E7: ='Закупка'!F7 -> 10 | F7: =IF(D7<>"",D7*E7,) | K7: ='Закупка'!T7 -> 8400731 | L7: ='Закупка'!U7 -> RS ROSA LA BELLE LOLOMARIK - flor | M7: ='Закупка'!V7 -> 181496
A8: ='Закупка'!A8 -> 1.5 | B8: ='Закупка'!B8 -> ROSA GARDEN PRISCILLA! | C8: ='Закупка'!R8 | D8: {=INDEX('Закупка'!G8:K8, $A$2)} | E8: ='Закупка'!F8 -> 5 | F8: =IF(D8<>"",D8*E8,) | K8: ='Закупка'!T8 -> 84001081 | L8: ='Закупка'!U8 -> ROSA PRISCILLA - flor | M8: ='Закупка'!V8
A9: ='Закупка'!A9 -> 1.6 | B9: ='Закупка'!B9 -> ROSA GARDEN MIX UHURU | C9: ='Закупка'!R9 | D9: {=INDEX('Закупка'!G9:K9, $A$2)} | E9: ='Закупка'!F9 -> 6 | F9: =IF(D9<>"",D9*E9,) | K9: ='Закупка'!T9 -> 84001157 | L9: ='Закупка'!U9 -> RISA GARDAN MIX - flor/3 | M9: ='Закупка'!V9
A10: ='Закупка'!A10 -> 1.7 | B10: ='Закупка'!B10 -> ROSA SPRAY CHIMO | C10: ='Закупка'!R10 | D10: {=INDEX('Закупка'!G10:K10, $A$2)} | E10: ='Закупка'!F10 -> 10 | F10: =IF(D10<>"",D10*E10,) | K10: ='Закупка'!T10 -> 8400828 | L10: ='Закупка'!U10 -> ROSA CHIMO - flor | M10: ='Закупка'!V10 -> 135409
A11: ='Закупка'!A11 -> 1.8 | B11: ='Закупка'!B11 -> ROSA SPRAY BIRDS NEST+ | C11: ='Закупка'!R11 | D11: {=INDEX('Закупка'!G11:K11, $A$2)} | E11: ='Закупка'!F11 -> 10 | F11: =IF(D11<>"",D11*E11,) | K11: ='Закупка'!T11 -> 84001078 | L11: ='Закупка'!U11 -> ROSA BIRDS NEST - flor | M11: ='Закупка'!V11
A12: ='Закупка'!A12 -> 1.9 | B12: ='Закупка'!B12 -> ROSA LARGE CELEB | C12: ='Закупка'!R12 | D12: {=INDEX('Закупка'!G12:K12, $A$2)} | E12: ='Закупка'!F12 -> 10 | F12: =IF(D12<>"",D12*E12,) | K12: ='Закупка'!T12 -> 84001044 | L12: ='Закупка'!U12 -> ROSA CELEBRATING HEATHER - flor | M12: ='Закупка'!V12
A13: ='Закупка'!A13 -> 1.10 | B13: ='Закупка'!B13 -> ARR CACTUS | C13: ='Закупка'!R13 | D13: {=INDEX('Закупка'!G13:K13, $A$2)} | E13: ='Закупка'!F13 -> 1 | F13: =IF(D13<>"",D13*E13,) | K13: ='Закупка'!T13 -> 8400594 | L13: ='Закупка'!U13 -> CACTUS - planta/22 | M13: ='Закупка'!V13 -> TEST 13 cactus
A14: ='Закупка'!A14 -> 1.11 | B14: ='Закупка'!B14 -> ALOE ARBO | C14: ='Закупка'!R14 | D14: {=INDEX('Закупка'!G14:K14, $A$2)} | E14: ='Закупка'!F14 -> 1 | F14: =IF(D14<>"",D14*E14,) | K14: ='Закупка'!T14 -> 84001156 | L14: ='Закупка'!U14 -> ALOE ARBO - planta/67 | M14: ='Закупка'!V14
... A98: ='Закупка'!A98 | B98: ='Закупка'!B98 | C98: ='Закупка'!R98 | D98: {=INDEX('Закупка'!G98:K98, $A$2)} | E98: ='Закупка'!F98 | F98: =IF(D98<>"",D98*E98,) | K98: ='Закупка'!T98 | L98: ='Закупка'!U98 | M98: ='Закупка'!V98
A99: ='Закупка'!A99 | B99: ='Закупка'!B99 | C99: ='Закупка'!R99 | D99: {=INDEX('Закупка'!G99:K99, $A$2)} | E99: ='Закупка'!F99 | F99: =IF(D99<>"",D99*E99,) | J99: =IF(H99<>"", H99-F99,) | K99: ='Закупка'!T99 | L99: ='Закупка'!U99 | M99: ='Закупка'!V99
A100: ='Закупка'!A100 | B100: ='Закупка'!B100 | C100: ='Закупка'!R100 | D100: {=INDEX('Закупка'!G100:K100, $A$2)} | E100: ='Закупка'!F100 | F100: =IF(D100<>"",D100*E100,) | J100: =IF(H100<>"", H100-F100,) | K100: ='Закупка'!T100 | L100: ='Закупка'!U100 | M100: ='Закупка'!V100
A101: ='Закупка'!A101 | B101: ='Закупка'!B101 | C101: ='Закупка'!R101 | D101: {=INDEX('Закупка'!G101:K101, $A$2)} | E101: ='Закупка'!F101 | F101: =IF(D101<>"",D101*E101,) | J101: =IF(H101<>"", H101-F101,) | K101: ='Закупка'!T101 | L101: ='Закупка'!U101 | M101: ='Закупка'!V101
A102: ='Закупка'!A102 | B102: ='Закупка'!B102 | C102: ='Закупка'!R102 | D102: {=INDEX('Закупка'!G102:K102, $A$2)} | E102: ='Закупка'!F102 | F102: =IF(D102<>"",D102*E102,) | J102: =IF(H102<>"", H102-F102,) | K102: ='Закупка'!T102 | L102: ='Закупка'!U102 | M102: ='Закупка'!V102
A103: ='Закупка'!A103 | B103: ='Закупка'!B103 | C103: ='Закупка'!R103 | D103: {=INDEX('Закупка'!G103:K103, $A$2)} | E103: ='Закупка'!F103 | F103: =IF(D103<>"",D103*E103,) | J103: =IF(H103<>"", H103-F103,) | K103: ='Закупка'!T103 | L103: ='Закупка'!U103 | M103: ='Закупка'!V103
A104: ='Закупка'!A104 | B104: ='Закупка'!B104 | C104: ='Закупка'!R104 | D104: {=INDEX('Закупка'!G104:K104, $A$2)} | E104: ='Закупка'!F104 | F104: =IF(D104<>"",D104*E104,) | J104: =IF(H104<>"", H104-F104,) | K104: ='Закупка'!T104 | L104: ='Закупка'!U104 | M104: ='Закупка'!V104
A105: ='Закупка'!A105 | B105: ='Закупка'!B105 | C105: ='Закупка'!R105 | D105: {=INDEX('Закупка'!G105:K105, $A$2)} | E105: ='Закупка'!F105 | F105: =IF(D105<>"",D105*E105,) | J105: =IF(H105<>"", H105-F105,) | K105: ='Закупка'!T105 | L105: ='Закупка'!U105 | M105: ='Закупка'!V105
A106: ='Закупка'!A106 | B106: ='Закупка'!B106 | C106: ='Закупка'!R106 | D106: {=INDEX('Закупка'!G106:K106, $A$2)} | E106: ='Закупка'!F106 | F106: =IF(D106<>"",D106*E106,) | J106: =IF(H106<>"", H106-F106,) | K106: ='Закупка'!T106 | L106: ='Закупка'!U106 | M106: ='Закупка'!V106
A107: ='Закупка'!A107 | B107: ='Закупка'!B107 | C107: ='Закупка'!R107 | D107: {=INDEX('Закупка'!G107:K107, $A$2)} | E107: ='Закупка'!F107 | F107: =IF(D107<>"",D107*E107,) | J107: =IF(H107<>"", H107-F107,) | K107: ='Закупка'!T107 | L107: ='Закупка'!U107 | M107: ='Закупка'!V107
A108: ='Закупка'!A108 | B108: ='Закупка'!B108 | C108: ='Закупка'!R108 | D108: {=INDEX('Закупка'!G108:K108, $A$2)} | E108: ='Закупка'!F108 | F108: =IF(D108<>"",D108*E108,) | J108: =IF(H108<>"", H108-F108,) | K108: ='Закупка'!T108 | L108: ='Закупка'!U108 | M108: ='Закупка'!V108
A109: ='Закупка'!A109 | B109: ='Закупка'!B109 | C109: ='Закупка'!R109 | D109: {=INDEX('Закупка'!G109:K109, $A$2)} | E109: ='Закупка'!F109 | F109: =IF(D109<>"",D109*E109,) | J109: =IF(H109<>"", H109-F109,) | K109: ='Закупка'!T109 | L109: ='Закупка'!U109 | M109: ='Закупка'!V109
A110: ='Закупка'!A110 | B110: ='Закупка'!B110 | C110: ='Закупка'!R110 | D110: {=INDEX('Закупка'!G110:K110, $A$2)} | E110: ='Закупка'!F110 | F110: =IF(D110<>"",D110*E110,) | J110: =IF(H110<>"", H110-F110,) | K110: ='Закупка'!T110 | L110: ='Закупка'!U110 | M110: ='Закупка'!V110
... A199: ='Закупка'!A199 | B199: ='Закупка'!B199 | C199: ='Закупка'!R199 | D199: {=INDEX('Закупка'!G199:K199, $A$2)} | E199: ='Закупка'!F199 | F199: =IF(D199<>"",D199*E199,) | J199: =IF(H199<>"", H199-F199,) | K199: ='Закупка'!T199 | L199: ='Закупка'!U199 | M199: ='Закупка'!V199

Sheet Gloria
A1: G | B1: =VLOOKUP(A1, Lookup!B:C, 2, FALSE) -> Gloria | D1: послали пачек | E1: ='Закупка'!F1 -> внтури пачки штук? | F1: послали штук товара | G1: ИМЯ флориста написать | J1: расхождение
A2: =MATCH(A1, 'Закупка'!G1:K1, 0) -> 4 | B2: ='Закупка'!B2 -> 45845 | G2: приехало пачек | H2: реально штук товара | I2: коментарий | K2: ='Закупка'!T1 -> Holded артикул | L2: ='Закупка'!U1 -> название с holded | M2: ='Закупка'!V1 -> codigo de fabricasion
A3: ='Закупка'!A3 | B3: ='Закупка'!B3 -> Фактура 1 | C3: ='Закупка'!R3 | D3: {=INDEX('Закупка'!G3:K3, $A$2)} | E3: ='Закупка'!F3 | F3: =IF(D3<>"",D3*E3,) | K3: ='Закупка'!T3 | L3: ='Закупка'!U3 | M3: ='Закупка'!V3
A4: ='Закупка'!A4 -> 1.1 | B4: ='Закупка'!B4 -> RANUNCULUS CLOONEY TUAREQ | C4: ='Закупка'!R4 | D4: {=INDEX('Закупка'!G4:K4, $A$2)} -> 3 | E4: ='Закупка'!F4 -> 10 | F4: =IF(D4<>"",D4*E4,) -> 30 | G4: 3 | H4: 30 | K4: ='Закупка'!T4 -> 8400518 | L4: ='Закупка'!U4 -> RANUNCULUS - Butterfly - flor | M4: ='Закупка'!V4 -> RANUBUBL, RANUBUSA, 174946, 147132, 126830
A5: ='Закупка'!A5 -> 1.2 | B5: ='Закупка'!B5 -> RANUNCULUS CLOONEY GRAND PASTEL | C5: ='Закупка'!R5 | D5: {=INDEX('Закупка'!G5:K5, $A$2)} | E5: ='Закупка'!F5 -> 10 | F5: =IF(D5<>"",D5*E5,) | K5: ='Закупка'!T5 -> 8400518 | L5: ='Закупка'!U5 -> RANUNCULUS - Butterfly - flor | M5: ='Закупка'!V5 -> RANUBUBL, RANUBUSA, 174946, 147132, 126830
A6: ='Закупка'!A6 -> 1.3 | B6: ='Закупка'!B6 -> ALSTROEMERIA SI SOFIENA | C6: ='Закупка'!R6 | D6: {=INDEX('Закупка'!G6:K6, $A$2)} -> 2 | E6: ='Закупка'!F6 -> 10 | F6: =IF(D6<>"",D6*E6,) -> 20 | G6: 2 | H6: 20 | K6: ='Закупка'!T6 -> 8400154 | L6: ='Закупка'!U6 -> ALSTROEMERIA - flor | M6: ='Закупка'!V6 -> 00027, 11920, 146548, 148465, ALS VA, 148462, 148466, 11920, ALS-P, 137896, 137077, 137894, 148289, 148469, ALSTROEMERIES ALSTROEMERIA, ALSP, 11920
A7: ='Закупка'!A7 -> 1.4 | B7: ='Закупка'!B7 -> ROSA LARGE BELLE ROSE | C7: ='Закупка'!R7 | D7: {=INDEX('Закупка'!G7:K7, $A$2)} | E7: ='Закупка'!F7 -> 10 | F7: =IF(D7<>"",D7*E7,) | K7: ='Закупка'!T7 -> 8400731 | L7: ='Закупка'!U7 -> RS ROSA LA BELLE LOLOMARIK - flor | M7: ='Закупка'!V7 -> 181496
A8: ='Закупка'!A8 -> 1.5 | B8: ='Закупка'!B8 -> ROSA GARDEN PRISCILLA! | C8: ='Закупка'!R8 | D8: {=INDEX('Закупка'!G8:K8, $A$2)} -> 2 | E8: ='Закупка'!F8 -> 5 | F8: =IF(D8<>"",D8*E8,) -> 10 | G8: 2 | H8: 10 | K8: ='Закупка'!T8 -> 84001081 | L8: ='Закупка'!U8 -> ROSA PRISCILLA - flor | M8: ='Закупка'!V8
A9: ='Закупка'!A9 -> 1.6 | B9: ='Закупка'!B9 -> ROSA GARDEN MIX UHURU | C9: ='Закупка'!R9 | D9: {=INDEX('Закупка'!G9:K9, $A$2)} | E9: ='Закупка'!F9 -> 6 | F9: =IF(D9<>"",D9*E9,) | K9: ='Закупка'!T9 -> 84001157 | L9: ='Закупка'!U9 -> RISA GARDAN MIX - flor/3 | M9: ='Закупка'!V9
A10: ='Закупка'!A10 -> 1.7 | B10: ='Закупка'!B10 -> ROSA SPRAY CHIMO | C10: ='Закупка'!R10 | D10: {=INDEX('Закупка'!G10:K10, $A$2)} -> 3 | E10: ='Закупка'!F10 -> 10 | F10: =IF(D10<>"",D10*E10,) -> 30 | G10: 3 | H10: 30 | K10: ='Закупка'!T10 -> 8400828 | L10: ='Закупка'!U10 -> ROSA CHIMO - flor | M10: ='Закупка'!V10 -> 135409
A11: ='Закупка'!A11 -> 1.8 | B11: ='Закупка'!B11 -> ROSA SPRAY BIRDS NEST+ | C11: ='Закупка'!R11 | D11: {=INDEX('Закупка'!G11:K11, $A$2)} -> 1 | E11: ='Закупка'!F11 -> 10 | F11: =IF(D11<>"",D11*E11,) -> 10 | G11: 1 | H11: 10 | K11: ='Закупка'!T11 -> 84001078 | L11: ='Закупка'!U11 -> ROSA BIRDS NEST - flor | M11: ='Закупка'!V11
A12: ='Закупка'!A12 -> 1.9 | B12: ='Закупка'!B12 -> ROSA LARGE CELEB | C12: ='Закупка'!R12 | D12: {=INDEX('Закупка'!G12:K12, $A$2)} -> 3 | E12: ='Закупка'!F12 -> 10 | F12: =IF(D12<>"",D12*E12,) -> 30 | G12: 3 | H12: 28 | K12: ='Закупка'!T12 -> 84001044 | L12: ='Закупка'!U12 -> ROSA CELEBRATING HEATHER - flor | M12: ='Закупка'!V12
A13: ='Закупка'!A13 -> 1.10 | B13: ='Закупка'!B13 -> ARR CACTUS | C13: ='Закупка'!R13 | D13: {=INDEX('Закупка'!G13:K13, $A$2)} -> 9 | E13: ='Закупка'!F13 -> 1 | F13: =IF(D13<>"",D13*E13,) -> 9 | G13: 1 | H13: 9 | K13: ='Закупка'!T13 -> 8400594 | L13: ='Закупка'!U13 -> CACTUS - planta/22 | M13: ='Закупка'!V13 -> TEST 13 cactus
A14: ='Закупка'!A14 -> 1.11 | B14: ='Закупка'!B14 -> ALOE ARBO | C14: ='Закупка'!R14 | D14: {=INDEX('Закупка'!G14:K14, $A$2)} -> 1 | E14: ='Закупка'!F14 -> 1 | F14: =IF(D14<>"",D14*E14,) -> 1 | G14: 1 | H14: 1 | K14: ='Закупка'!T14 -> 84001156 | L14: ='Закупка'!U14 -> ALOE ARBO - planta/67 | M14: ='Закупка'!V14
A15: ='Закупка'!A15 -> 1.12 | B15: ='Закупка'!B15 -> ALOE ARBO | C15: ='Закупка'!R15 | D15: {=INDEX('Закупка'!G15:K15, $A$2)} -> 4 | E15: ='Закупка'!F15 -> 1 | F15: =IF(D15<>"",D15*E15,) -> 4 | G15: 1 | H15: 4 | K15: ='Закупка'!T15 -> 84001155 | L15: ='Закупка'!U15 -> ALOE ARBO - planta/47 | M15: ='Закупка'!V15
A16: ='Закупка'!A16 -> 1.13 | B16: ='Закупка'!B16 -> ARR2 MB GROEN IJZER REK 1 BOL | C16: ='Закупка'!R16 | D16: {=INDEX('Закупка'!G16:K16, $A$2)} -> 4 | E16: ='Закупка'!F16 -> 1 | F16: =IF(D16<>"",D16*E16,) -> 4 | G16: 1 | H16: 4 | K16: ='Закупка'!T16 -> 8400410 | L16: ='Закупка'!U16 -> SUCCULENTUS T16, T22 - MIX - planta/22 | M16: ='Закупка'!V16 -> 6CRASA22, 54, CRASS16
A17: ='Закупка'!A17 -> 1.14 | B17: ='Закупка'!B17 -> ARR NARCISSUS TETE-A-TETE | C17: ='Закупка'!R17 | D17: {=INDEX('Закупка'!G17:K17, $A$2)} -> 6 | E17: ='Закупка'!F17 -> 1 | F17: =IF(D17<>"",D17*E17,) -> 6 | G17: 1 | H17: 6 | K17: ='Закупка'!T17 -> 84001152 | L17: ='Закупка'!U17 -> NARCISO TETE-A-TETE - composición/14 | M17: ='Закупка'!V17
A18: ='Закупка'!A18 -> 1.15 | B18: ='Закупка'!B18 -> ARR NARCISSUS | C18: ='Закупка'!R18 | D18: {=INDEX('Закупка'!G18:K18, $A$2)} -> 4 | E18: ='Закупка'!F18 -> 1 | F18: =IF(D18<>"",D18*E18,) -> 4 | G18: 1 | H18: 4 | K18: ='Закупка'!T18 -> 84001038 | L18: ='Закупка'!U18 -> NARCIS MASCOTA - planta /17 | M18: ='Закупка'!V18
A19: ='Закупка'!A19 -> 1.16 | B19: ='Закупка'!B19 -> ARR2 PL KER BAROK DRACENA | C19: ='Закупка'!R19 | D19: {=INDEX('Закупка'!G19:K19, $A$2)} -> 4 | E19: ='Закупка'!F19 -> 1 | F19: =IF(D19<>"",D19*E19,) -> 4 | G19: 1 | H19: 4 | K19: ='Закупка'!T19 -> 84001154 | L19: ='Закупка'!U19 -> COMPOSITION DE DRECENA - planta/38 | M19: ='Закупка'!V19
A20: ='Закупка'!A20 -> 1.17 | B20: ='Закупка'!B20 -> ARR2 PL KER BAROK DRACENA | C20: ='Закупка'!R20 | D20: {=INDEX('Закупка'!G20:K20, $A$2)} | E20: ='Закупка'!F20 -> 1 | F20: =IF(D20<>"",D20*E20,) | K20: ='Закупка'!T20 -> 84001154 | L20: ='Закупка'!U20 -> COMPOSITION DE DRECENA - planta/38 | M20: ='Закупка'!V20
A21: ='Закупка'!A21 -> 1.18 | B21: ='Закупка'!B21 -> ARR2 PL GLAS CILINDER PHAL PAARS | C21: ='Закупка'!R21 | D21: {=INDEX('Закупка'!G21:K21, $A$2)} -> 2 | E21: ='Закупка'!F21 -> 1 | F21: =IF(D21<>"",D21*E21,) -> 2 | G21: 2 | H21: 2 | K21: ='Закупка'!T21 -> 84001153 | L21: ='Закупка'!U21 -> ARRANGEMENT DE PHALAENOPSIS - composición/56 | M21: ='Закупка'!V21
A22: ='Закупка'!A22 -> 1.19 | B22: ='Закупка'!B22 -> CRASSULA OVATA | C22: ='Закупка'!R22 | D22: {=INDEX('Закупка'!G22:K22, $A$2)} -> 1 | E22: ='Закупка'!F22 -> 1 | F22: =IF(D22<>"",D22*E22,) -> 1 | G22: 1 | H22: 1 | K22: ='Закупка'!T22 -> 8400365 | L22: ='Закупка'!U22 -> ARBOL DE JADE T25 -planta/120 | M22: ='Закупка'!V22 -> ARBOL DE JADE GRANDE (Crassula Ovata) T-25
A23: ='Закупка'!A23 -> 1.20 | B23: ='Закупка'!B23 -> CRASSULA OVATA | C23: ='Закупка'!R23 | D23: {=INDEX('Закупка'!G23:K23, $A$2)} | E23: ='Закупка'!F23 -> 1 | F23: =IF(D23<>"",D23*E23,) | K23: ='Закупка'!T23 -> 8400365 | L23: ='Закупка'!U23 -> ARBOL DE JADE T25 -planta/188 | M23: ='Закупка'!V23 -> ARBOL DE JADE GRANDE (Crassula Ovata) T-25
A24: ='Закупка'!A24 -> 1.21 | B24: ='Закупка'!B24 -> CODIAEUM VARI MRS ICETON | C24: ='Закупка'!R24 | D24: {=INDEX('Закупка'!G24:K24, $A$2)} -> 3 | E24: ='Закупка'!F24 -> 1 | F24: =IF(D24<>"",D24*E24,) -> 3 | G24: 3 | H24: 3 | K24: ='Закупка'!T24 -> 8400558 | L24: ='Закупка'!U24 -> CROTON 50cm - Petra - planta/36 | M24: ='Закупка'!V24 -> 81945, CROMA20
A25: ='Закупка'!A25 -> 1.22 | B25: ='Закупка'!B25 -> LAVANDULA STOE ANOUK | C25: ='Закупка'!R25 | D25: {=INDEX('Закупка'!G25:K25, $A$2)} | E25: ='Закупка'!F25 -> 1 | F25: =IF(D25<>"",D25*E25,) | K25: ='Закупка'!T25 -> 8400357 | L25: ='Закупка'!U25 -> LAVANDULA T13 - planta | M25: ='Закупка'!V25 -> LAV13 LAVANDULA T-13, 42454
A26: ='Закупка'!A26 -> 1.23 | B26: ='Закупка'!B26 -> KALANCHOE LUCKY BELLS | C26: ='Закупка'!R26 | D26: {=INDEX('Закупка'!G26:K26, $A$2)} -> 6 | E26: ='Закупка'!F26 -> 1 | F26: =IF(D26<>"",D26*E26,) -> 6 | G26: 1 | H26: 6 | K26: ='Закупка'!T26 -> 8400448 | L26: ='Закупка'!U26 -> KALANCHOE T25 - Pumila - planta/18 | M26: ='Закупка'!V26 -> KAL-P KALANCHOE PUMILA T-25 planta, KCALT
A27: ='Закупка'!A27 -> 1.24 | B27: ='Закупка'!B27 -> EUPHORBIA TRIGONA | C27: ='Закупка'!R27 | D27: {=INDEX('Закупка'!G27:K27, $A$2)} | E27: ='Закупка'!F27 -> 1 | F27: =IF(D27<>"",D27*E27,) | K27: ='Закупка'!T27 -> 8400556 | L27: ='Закупка'!U27 -> EUPHORBIA 30cm -Milii - planta/22 | M27: ='Закупка'!V27 -> 174581, EUV
A28: ='Закупка'!A28 -> 1.25 | B28: ='Закупка'!B28 -> PTPB6537 ARRANGEMENTEN PASEN | C28: ='Закупка'!R28 | D28: {=INDEX('Закупка'!G28:K28, $A$2)} -> 1 | E28: ='Закупка'!F28 -> 1 | F28: =IF(D28<>"",D28*E28,) -> 1 | G28: 1 | H28: 1 | K28: ='Закупка'!T28 -> 84001153 | L28: ='Закупка'!U28 -> ARRANGEMENT DE PHALAENOPSIS - composición/56 | M28: ='Закупка'!V28
A29: ='Закупка'!A29 -> 1.26 | B29: ='Закупка'!B29 -> PTPB6525 ARRANGEMENTEN PASEN | C29: ='Закупка'!R29 | D29: {=INDEX('Закупка'!G29:K29, $A$2)} -> 1 | E29: ='Закупка'!F29 -> 1 | F29: =IF(D29<>"",D29*E29,) -> 1 | G29: 1 | H29: 1 | K29: ='Закупка'!T29 -> 84001153 | L29: ='Закупка'!U29 -> ARRANGEMENT DE PHALAENOPSIS - composición/56 | M29: ='Закупка'!V29
A30: ='Закупка'!A30 -> 1.27 | B30: ='Закупка'!B30 -> PHALAENOPSIS OTHER YELLOW | C30: ='Закупка'!R30 | D30: {=INDEX('Закупка'!G30:K30, $A$2)} -> 6 | E30: ='Закупка'!F30 -> 1 | F30: =IF(D30<>"",D30*E30,) -> 6 | G30: 6 | H30: 6 | K30: ='Закупка'!T30 -> 8400391 | L30: ='Закупка'!U30 -> PHALAENOPSIS MIX - planta/28 | M30: ='Закупка'!V30 -> 161202, 179376, 144102, 179304, 191963, 135419, 182797, 127000, 191284
A31: ='Закупка'!A31 -> 1.28 | B31: ='Закупка'!B31 -> SUCCULENTEN OTHER | C31: ='Закупка'!R31 | D31: {=INDEX('Закупка'!G31:K31, $A$2)} | E31: ='Закупка'!F31 -> 1 | F31: =IF(D31<>"",D31*E31,) | K31: ='Закупка'!T31 -> 8400591 | L31: ='Закупка'!U31 -> SUCCULENTUS OTHER - planta/28 | M31: ='Закупка'!V31 -> CRASSCI-9, AEON.012
A32: ='Закупка'!A32 -> 1.29 | B32: ='Закупка'!B32 -> RHIPSALIS MIX | C32: ='Закупка'!R32 | D32: {=INDEX('Закупка'!G32:K32, $A$2)} -> 12 | E32: ='Закупка'!F32 -> 1 | F32: =IF(D32<>"",D32*E32,) -> 12 | G32: 1 | H32: 12 | K32: ='Закупка'!T32 -> 8400895 | L32: ='Закупка'!U32 -> RHIPSALIS MIX - T17 planta colganta | M32: ='Закупка'!V32 -> 83612
A33: ='Закупка'!A33 | B33: ='Закупка'!B33 | C33: ='Закупка'!R33 | D33: {=INDEX('Закупка'!G33:K33, $A$2)} | E33: ='Закупка'!F33 | F33: =IF(D33<>"",D33*E33,) | K33: ='Закупка'!T33 | L33: ='Закупка'!U33 | M33: ='Закупка'!V33
A34: ='Закупка'!A34 | B34: ='Закупка'!B34 | C34: ='Закупка'!R34 | D34: {=INDEX('Закупка'!G34:K34, $A$2)} | E34: ='Закупка'!F34 | F34: =IF(D34<>"",D34*E34,) | K34: ='Закупка'!T34 | L34: ='Закупка'!U34 | M34: ='Закупка'!V34
A35: ='Закупка'!A35 | B35: ='Закупка'!B35 | C35: ='Закупка'!R35 | D35: {=INDEX('Закупка'!G35:K35, $A$2)} | E35: ='Закупка'!F35 | F35: =IF(D35<>"",D35*E35,) | K35: ='Закупка'!T35 | L35: ='Закупка'!U35 | M35: ='Закупка'!V35
A36: ='Закупка'!A36 | B36: ='Закупка'!B36 | C36: ='Закупка'!R36 | D36: {=INDEX('Закупка'!G36:K36, $A$2)} | E36: ='Закупка'!F36 | F36: =IF(D36<>"",D36*E36,) | K36: ='Закупка'!T36 | L36: ='Закупка'!U36 | M36: ='Закупка'!V36
A37: ='Закупка'!A37 | B37: ='Закупка'!B37 | C37: ='Закупка'!R37 | D37: {=INDEX('Закупка'!G37:K37, $A$2)} | E37: ='Закупка'!F37 | F37: =IF(D37<>"",D37*E37,) | K37: ='Закупка'!T37 | L37: ='Закупка'!U37 | M37: ='Закупка'!V37
A38: ='Закупка'!A38 | B38: ='Закупка'!B38 | C38: ='Закупка'!R38 | D38: {=INDEX('Закупка'!G38:K38, $A$2)} | E38: ='Закупка'!F38 | F38: =IF(D38<>"",D38*E38,) | K38: ='Закупка'!T38 | L38: ='Закупка'!U38 | M38: ='Закупка'!V38
A39: ='Закупка'!A39 | B39: ='Закупка'!B39 | C39: ='Закупка'!R39 | D39: {=INDEX('Закупка'!G39:K39, $A$2)} | E39: ='Закупка'!F39 | F39: =IF(D39<>"",D39*E39,) | K39: ='Закупка'!T39 | L39: ='Закупка'!U39 | M39: ='Закупка'!V39
A40: ='Закупка'!A40 | B40: ='Закупка'!B40 | C40: ='Закупка'!R40 | D40: {=INDEX('Закупка'!G40:K40, $A$2)} | E40: ='Закупка'!F40 | F40: =IF(D40<>"",D40*E40,) | K40: ='Закупка'!T40 | L40: ='Закупка'!U40 | M40: ='Закупка'!V40
A41: ='Закупка'!A41 | B41: ='Закупка'!B41 | C41: ='Закупка'!R41 | D41: {=INDEX('Закупка'!G41:K41, $A$2)} | E41: ='Закупка'!F41 | F41: =IF(D41<>"",D41*E41,) | K41: ='Закупка'!T41 | L41: ='Закупка'!U41 | M41: ='Закупка'!V41
A42: ='Закупка'!A42 | B42: ='Закупка'!B42 | C42: ='Закупка'!R42 | D42: {=INDEX('Закупка'!G42:K42, $A$2)} | E42: ='Закупка'!F42 | F42: =IF(D42<>"",D42*E42,) | K42: ='Закупка'!T42 | L42: ='Закупка'!U42 | M42: ='Закупка'!V42
A43: ='Закупка'!A43 | B43: ='Закупка'!B43 | C43: ='Закупка'!R43 | D43: {=INDEX('Закупка'!G43:K43, $A$2)} | E43: ='Закупка'!F43 | F43: =IF(D43<>"",D43*E43,) | K43: ='Закупка'!T43 | L43: ='Закупка'!U43 | M43: ='Закупка'!V43
A44: ='Закупка'!A44 | B44: ='Закупка'!B44 | C44: ='Закупка'!R44 | D44: {=INDEX('Закупка'!G44:K44, $A$2)} | E44: ='Закупка'!F44 | F44: =IF(D44<>"",D44*E44,) | K44: ='Закупка'!T44 | L44: ='Закупка'!U44 | M44: ='Закупка'!V44
... A113: ='Закупка'!A113 | B113: ='Закупка'!B113 | C113: ='Закупка'!R113 | D113: {=INDEX('Закупка'!G113:K113, $A$2)} | E113: ='Закупка'!F113 | F113: =IF(D113<>"",D113*E113,) | K113: ='Закупка'!T113 | L113: ='Закупка'!U113 | M113: ='Закупка'!V113
A114: ='Закупка'!A114 | B114: ='Закупка'!B114 | C114: ='Закупка'!R114 | D114: {=INDEX('Закупка'!G114:K114, $A$2)} | E114: ='Закупка'!F114 | F114: =IF(D114<>"",D114*E114,) | J114: =IF(H114<>"", H114-F114,) | K114: ='Закупка'!T114 | L114: ='Закупка'!U114 | M114: ='Закупка'!V114
A115: ='Закупка'!A115 | B115: ='Закупка'!B115 | C115: ='Закупка'!R115 | D115: {=INDEX('Закупка'!G115:K115, $A$2)} | E115: ='Закупка'!F115 | F115: =IF(D115<>"",D115*E115,) | J115: =IF(H115<>"", H115-F115,) | K115: ='Закупка'!T115 | L115: ='Закупка'!U115 | M115: ='Закупка'!V115
A116: ='Закупка'!A116 | B116: ='Закупка'!B116 | C116: ='Закупка'!R116 | D116: {=INDEX('Закупка'!G116:K116, $A$2)} | E116: ='Закупка'!F116 | F116: =IF(D116<>"",D116*E116,) | J116: =IF(H116<>"", H116-F116,) | K116: ='Закупка'!T116 | L116: ='Закупка'!U116 | M116: ='Закупка'!V116
A117: ='Закупка'!A117 | B117: ='Закупка'!B117 | C117: ='Закупка'!R117 | D117: {=INDEX('Закупка'!G117:K117, $A$2)} | E117: ='Закупка'!F117 | F117: =IF(D117<>"",D117*E117,) | J117: =IF(H117<>"", H117-F117,) | K117: ='Закупка'!T117 | L117: ='Закупка'!U117 | M117: ='Закупка'!V117
A118: ='Закупка'!A118 | B118: ='Закупка'!B118 | C118: ='Закупка'!R118 | D118: {=INDEX('Закупка'!G118:K118, $A$2)} | E118: ='Закупка'!F118 | F118: =IF(D118<>"",D118*E118,) | J118: =IF(H118<>"", H118-F118,) | K118: ='Закупка'!T118 | L118: ='Закупка'!U118 | M118: ='Закупка'!V118
A119: ='Закупка'!A119 | B119: ='Закупка'!B119 | C119: ='Закупка'!R119 | D119: {=INDEX('Закупка'!G119:K119, $A$2)} | E119: ='Закупка'!F119 | F119: =IF(D119<>"",D119*E119,) | J119: =IF(H119<>"", H119-F119,) | K119: ='Закупка'!T119 | L119: ='Закупка'!U119 | M119: ='Закупка'!V119
A120: ='Закупка'!A120 | B120: ='Закупка'!B120 | C120: ='Закупка'!R120 | D120: {=INDEX('Закупка'!G120:K120, $A$2)} | E120: ='Закупка'!F120 | F120: =IF(D120<>"",D120*E120,) | J120: =IF(H120<>"", H120-F120,) | K120: ='Закупка'!T120 | L120: ='Закупка'!U120 | M120: ='Закупка'!V120
A121: ='Закупка'!A121 | B121: ='Закупка'!B121 | C121: ='Закупка'!R121 | D121: {=INDEX('Закупка'!G121:K121, $A$2)} | E121: ='Закупка'!F121 | F121: =IF(D121<>"",D121*E121,) | J121: =IF(H121<>"", H121-F121,) | K121: ='Закупка'!T121 | L121: ='Закупка'!U121 | M121: ='Закупка'!V121
A122: ='Закупка'!A122 | B122: ='Закупка'!B122 | C122: ='Закупка'!R122 | D122: {=INDEX('Закупка'!G122:K122, $A$2)} | E122: ='Закупка'!F122 | F122: =IF(D122<>"",D122*E122,) | J122: =IF(H122<>"", H122-F122,) | K122: ='Закупка'!T122 | L122: ='Закупка'!U122 | M122: ='Закупка'!V122
A123: ='Закупка'!A123 | B123: ='Закупка'!B123 | C123: ='Закупка'!R123 | D123: {=INDEX('Закупка'!G123:K123, $A$2)} | E123: ='Закупка'!F123 | F123: =IF(D123<>"",D123*E123,) | J123: =IF(H123<>"", H123-F123,) | K123: ='Закупка'!T123 | L123: ='Закупка'!U123 | M123: ='Закупка'!V123
A124: ='Закупка'!A124 | B124: ='Закупка'!B124 | C124: ='Закупка'!R124 | D124: {=INDEX('Закупка'!G124:K124, $A$2)} | E124: ='Закупка'!F124 | F124: =IF(D124<>"",D124*E124,) | J124: =IF(H124<>"", H124-F124,) | K124: ='Закупка'!T124 | L124: ='Закупка'!U124 | M124: ='Закупка'!V124
A125: ='Закупка'!A125 | B125: ='Закупка'!B125 | C125: ='Закупка'!R125 | D125: {=INDEX('Закупка'!G125:K125, $A$2)} | E125: ='Закупка'!F125 | F125: =IF(D125<>"",D125*E125,) | J125: =IF(H125<>"", H125-F125,) | K125: ='Закупка'!T125 | L125: ='Закупка'!U125 | M125: ='Закупка'!V125
... A199: ='Закупка'!A199 | B199: ='Закупка'!B199 | C199: ='Закупка'!R199 | D199: {=INDEX('Закупка'!G199:K199, $A$2)} | E199: ='Закупка'!F199 | F199: =IF(D199<>"",D199*E199,) | J199: =IF(H199<>"", H199-F199,) | K199: ='Закупка'!T199 | L199: ='Закупка'!U199 | M199: ='Закупка'!V199

Sheet Blau
A1: B | B1: =VLOOKUP(A1, Lookup!B:C, 2, FALSE) -> Blau | D1: послали пачек | E1: ='Закупка'!F1 -> внтури пачки штук? | F1: послали штук товара | G1: ИМЯ флориста написать | J1: расхождение
A2: =MATCH(A1, 'Закупка'!G1:K1, 0) -> 5 | B2: ='Закупка'!B2 -> 45845 | G2: приехало пачек | H2: реально штук товара | I2: коментарий | K2: ='Закупка'!T1 -> Holded артикул | L2: ='Закупка'!U1 -> название с holded | M2: ='Закупка'!V1 -> codigo de fabricasion
A3: ='Закупка'!A3 | B3: ='Закупка'!B3 -> Фактура 1 | C3: ='Закупка'!R3 | D3: {=INDEX('Закупка'!G3:K3, $A$2)} | E3: ='Закупка'!F3 | F3: =IF(D3<>"",D3*E3,) | K3: ='Закупка'!T3 | L3: ='Закупка'!U3 | M3: ='Закупка'!V3
A4: ='Закупка'!A4 -> 1.1 | B4: ='Закупка'!B4 -> RANUNCULUS CLOONEY TUAREQ | C4: ='Закупка'!R4 | D4: {=INDEX('Закупка'!G4:K4, $A$2)} | E4: ='Закупка'!F4 -> 10 | F4: =IF(D4<>"",D4*E4,) | K4: ='Закупка'!T4 -> 8400518 | L4: ='Закупка'!U4 -> RANUNCULUS - Butterfly - flor | M4: ='Закупка'!V4 -> RANUBUBL, RANUBUSA, 174946, 147132, 126830
A5: ='Закупка'!A5 -> 1.2 | B5: ='Закупка'!B5 -> RANUNCULUS CLOONEY GRAND PASTEL | C5: ='Закупка'!R5 | D5: {=INDEX('Закупка'!G5:K5, $A$2)} -> 6 | E5: ='Закупка'!F5 -> 10 | F5: =IF(D5<>"",D5*E5,) -> 60 | G5: 6 | H5: 48 | K5: ='Закупка'!T5 -> 8400518 | L5: ='Закупка'!U5 -> RANUNCULUS - Butterfly - flor | M5: ='Закупка'!V5 -> RANUBUBL, RANUBUSA, 174946, 147132, 126830
A6: ='Закупка'!A6 -> 1.3 | B6: ='Закупка'!B6 -> ALSTROEMERIA SI SOFIENA | C6: ='Закупка'!R6 | D6: {=INDEX('Закупка'!G6:K6, $A$2)} -> 2 | E6: ='Закупка'!F6 -> 10 | F6: =IF(D6<>"",D6*E6,) -> 20 | G6: 2 | H6: 18 | K6: ='Закупка'!T6 -> 8400154 | L6: ='Закупка'!U6 -> ALSTROEMERIA - flor | M6: ='Закупка'!V6 -> 00027, 11920, 146548, 148465, ALS VA, 148462, 148466, 11920, ALS-P, 137896, 137077, 137894, 148289, 148469, ALSTROEMERIES ALSTROEMERIA, ALSP, 11920
A7: ='Закупка'!A7 -> 1.4 | B7: ='Закупка'!B7 -> ROSA LARGE BELLE ROSE | C7: ='Закупка'!R7 | D7: {=INDEX('Закупка'!G7:K7, $A$2)} -> 6 | E7: ='Закупка'!F7 -> 10 | F7: =IF(D7<>"",D7*E7,) -> 60 | G7: 6 | H7: 60 | K7: ='Закупка'!T7 -> 8400731 | L7: ='Закупка'!U7 -> RS ROSA LA BELLE LOLOMARIK - flor | M7: ='Закупка'!V7 -> 181496
A8: ='Закупка'!A8 -> 1.5 | B8: ='Закупка'!B8 -> ROSA GARDEN PRISCILLA! | C8: ='Закупка'!R8 | D8: {=INDEX('Закупка'!G8:K8, $A$2)} -> 4 | E8: ='Закупка'!F8 -> 5 | F8: =IF(D8<>"",D8*E8,) -> 20 | G8: 4 | H8: 20 | K8: ='Закупка'!T8 -> 84001081 | L8: ='Закупка'!U8 -> ROSA PRISCILLA - flor | M8: ='Закупка'!V8
A9: ='Закупка'!A9 -> 1.6 | B9: ='Закупка'!B9 -> ROSA GARDEN MIX UHURU | C9: ='Закупка'!R9 | D9: {=INDEX('Закупка'!G9:K9, $A$2)} -> 8 | E9: ='Закупка'!F9 -> 6 | F9: =IF(D9<>"",D9*E9,) -> 48 | G9: 8 | H9: 46 | K9: ='Закупка'!T9 -> 84001157 | L9: ='Закупка'!U9 -> RISA GARDAN MIX - flor/3 | M9: ='Закупка'!V9
A10: ='Закупка'!A10 -> 1.7 | B10: ='Закупка'!B10 -> ROSA SPRAY CHIMO | C10: ='Закупка'!R10 | D10: {=INDEX('Закупка'!G10:K10, $A$2)} -> 3 | E10: ='Закупка'!F10 -> 10 | F10: =IF(D10<>"",D10*E10,) -> 30 | G10: 3 | H10: 30 | K10: ='Закупка'!T10 -> 8400828 | L10: ='Закупка'!U10 -> ROSA CHIMO - flor | M10: ='Закупка'!V10 -> 135409
A11: ='Закупка'!A11 -> 1.8 | B11: ='Закупка'!B11 -> ROSA SPRAY BIRDS NEST+ | C11: ='Закупка'!R11 | D11: {=INDEX('Закупка'!G11:K11, $A$2)} -> 3 | E11: ='Закупка'!F11 -> 10 | F11: =IF(D11<>"",D11*E11,) -> 30 | G11: 3 | H11: 30 | K11: ='Закупка'!T11 -> 84001078 | L11: ='Закупка'!U11 -> ROSA BIRDS NEST - flor | M11: ='Закупка'!V11
A12: ='Закупка'!A12 -> 1.9 | B12: ='Закупка'!B12 -> ROSA LARGE CELEB | C12: ='Закупка'!R12 | D12: {=INDEX('Закупка'!G12:K12, $A$2)} | E12: ='Закупка'!F12 -> 10 | F12: =IF(D12<>"",D12*E12,) | K12: ='Закупка'!T12 -> 84001044 | L12: ='Закупка'!U12 -> ROSA CELEBRATING HEATHER - flor | M12: ='Закупка'!V12
A13: ='Закупка'!A13 -> 1.10 | B13: ='Закупка'!B13 -> ARR CACTUS | C13: ='Закупка'!R13 | D13: {=INDEX('Закупка'!G13:K13, $A$2)} -> 9 | E13: ='Закупка'!F13 -> 1 | F13: =IF(D13<>"",D13*E13,) -> 9 | G13: 9 | H13: 9 | K13: ='Закупка'!T13 -> 8400594 | L13: ='Закупка'!U13 -> CACTUS - planta/22 | M13: ='Закупка'!V13 -> TEST 13 cactus
A14: ='Закупка'!A14 -> 1.11 | B14: ='Закупка'!B14 -> ALOE ARBO | C14: ='Закупка'!R14 | D14: {=INDEX('Закупка'!G14:K14, $A$2)} | E14: ='Закупка'!F14 -> 1 | F14: =IF(D14<>"",D14*E14,) | K14: ='Закупка'!T14 -> 84001156 | L14: ='Закупка'!U14 -> ALOE ARBO - planta/67 | M14: ='Закупка'!V14
A15: ='Закупка'!A15 -> 1.12 | B15: ='Закупка'!B15 -> ALOE ARBO | C15: ='Закупка'!R15 | D15: {=INDEX('Закупка'!G15:K15, $A$2)} -> 4 | E15: ='Закупка'!F15 -> 1 | F15: =IF(D15<>"",D15*E15,) -> 4 | G15: 4 | H15: 4 | K15: ='Закупка'!T15 -> 84001155 | L15: ='Закупка'!U15 -> ALOE ARBO - planta/47 | M15: ='Закупка'!V15
A16: ='Закупка'!A16 -> 1.13 | B16: ='Закупка'!B16 -> ARR2 MB GROEN IJZER REK 1 BOL | C16: ='Закупка'!R16 | D16: {=INDEX('Закупка'!G16:K16, $A$2)} -> 4 | E16: ='Закупка'!F16 -> 1 | F16: =IF(D16<>"",D16*E16,) -> 4 | G16: 4 | H16: 4 | K16: ='Закупка'!T16 -> 8400410 | L16: ='Закупка'!U16 -> SUCCULENTUS T16, T22 - MIX - planta/22 | M16: ='Закупка'!V16 -> 6CRASA22, 54, CRASS16
A17: ='Закупка'!A17 -> 1.14 | B17: ='Закупка'!B17 -> ARR NARCISSUS TETE-A-TETE | C17: ='Закупка'!R17 | D17: {=INDEX('Закупка'!G17:K17, $A$2)} -> 6 | E17: ='Закупка'!F17 -> 1 | F17: =IF(D17<>"",D17*E17,) -> 6 | G17: 6 | H17: 6 | K17: ='Закупка'!T17 -> 84001152 | L17: ='Закупка'!U17 -> NARCISO TETE-A-TETE - composición/14 | M17: ='Закупка'!V17
A18: ='Закупка'!A18 -> 1.15 | B18: ='Закупка'!B18 -> ARR NARCISSUS | C18: ='Закупка'!R18 | D18: {=INDEX('Закупка'!G18:K18, $A$2)} -> 4 | E18: ='Закупка'!F18 -> 1 | F18: =IF(D18<>"",D18*E18,) -> 4 | G18: 4 | H18: 4 | K18: ='Закупка'!T18 -> 84001038 | L18: ='Закупка'!U18 -> NARCIS MASCOTA - planta /17 | M18: ='Закупка'!V18
A19: ='Закупка'!A19 -> 1.16 | B19: ='Закупка'!B19 -> ARR2 PL KER BAROK DRACENA | C19: ='Закупка'!R19 | D19: {=INDEX('Закупка'!G19:K19, $A$2)} | E19: ='Закупка'!F19 -> 1 | F19: =IF(D19<>"",D19*E19,) | K19: ='Закупка'!T19 -> 84001154 | L19: ='Закупка'!U19 -> COMPOSITION DE DRECENA - planta/38 | M19: ='Закупка'!V19
A20: ='Закупка'!A20 -> 1.17 | B20: ='Закупка'!B20 -> ARR2 PL KER BAROK DRACENA | C20: ='Закупка'!R20 | D20: {=INDEX('Закупка'!G20:K20, $A$2)} -> 4 | E20: ='Закупка'!F20 -> 1 | F20: =IF(D20<>"",D20*E20,) -> 4 | G20: 4 | H20: 4 | K20: ='Закупка'!T20 -> 84001154 | L20: ='Закупка'!U20 -> COMPOSITION DE DRECENA - planta/38 | M20: ='Закупка'!V20
A21: ='Закупка'!A21 -> 1.18 | B21: ='Закупка'!B21 -> ARR2 PL GLAS CILINDER PHAL PAARS | C21: ='Закупка'!R21 | D21: {=INDEX('Закупка'!G21:K21, $A$2)} -> 2 | E21: ='Закупка'!F21 -> 1 | F21: =IF(D21<>"",D21*E21,) -> 2 | G21: 2 | H21: 2 | K21: ='Закупка'!T21 -> 84001153 | L21: ='Закупка'!U21 -> ARRANGEMENT DE PHALAENOPSIS - composición/56 | M21: ='Закупка'!V21
A22: ='Закупка'!A22 -> 1.19 | B22: ='Закупка'!B22 -> CRASSULA OVATA | C22: ='Закупка'!R22 | D22: {=INDEX('Закупка'!G22:K22, $A$2)} | E22: ='Закупка'!F22 -> 1 | F22: =IF(D22<>"",D22*E22,) | K22: ='Закупка'!T22 -> 8400365 | L22: ='Закупка'!U22 -> ARBOL DE JADE T25 -planta/120 | M22: ='Закупка'!V22 -> ARBOL DE JADE GRANDE (Crassula Ovata) T-25
A23: ='Закупка'!A23 -> 1.20 | B23: ='Закупка'!B23 -> CRASSULA OVATA | C23: ='Закупка'!R23 | D23: {=INDEX('Закупка'!G23:K23, $A$2)} -> 1 | E23: ='Закупка'!F23 -> 1 | F23: =IF(D23<>"",D23*E23,) -> 1 | G23: 1 | H23: 1 | K23: ='Закупка'!T23 -> 8400365 | L23: ='Закупка'!U23 -> ARBOL DE JADE T25 -planta/188 | M23: ='Закупка'!V23 -> ARBOL DE JADE GRANDE (Crassula Ovata) T-25
A24: ='Закупка'!A24 -> 1.21 | B24: ='Закупка'!B24 -> CODIAEUM VARI MRS ICETON | C24: ='Закупка'!R24 | D24: {=INDEX('Закупка'!G24:K24, $A$2)} | E24: ='Закупка'!F24 -> 1 | F24: =IF(D24<>"",D24*E24,) | K24: ='Закупка'!T24 -> 8400558 | L24: ='Закупка'!U24 -> CROTON 50cm - Petra - planta/36 | M24: ='Закупка'!V24 -> 81945, CROMA20
A25: ='Закупка'!A25 -> 1.22 | B25: ='Закупка'!B25 -> LAVANDULA STOE ANOUK | C25: ='Закупка'!R25 | D25: {=INDEX('Закупка'!G25:K25, $A$2)} -> 6 | E25: ='Закупка'!F25 -> 1 | F25: =IF(D25<>"",D25*E25,) -> 6 | G25: 6 | H25: 6 | K25: ='Закупка'!T25 -> 8400357 | L25: ='Закупка'!U25 -> LAVANDULA T13 - planta | M25: ='Закупка'!V25 -> LAV13 LAVANDULA T-13, 42454
A26: ='Закупка'!A26 -> 1.23 | B26: ='Закупка'!B26 -> KALANCHOE LUCKY BELLS | C26: ='Закупка'!R26 | D26: {=INDEX('Закупка'!G26:K26, $A$2)} | E26: ='Закупка'!F26 -> 1 | F26: =IF(D26<>"",D26*E26,) | K26: ='Закупка'!T26 -> 8400448 | L26: ='Закупка'!U26 -> KALANCHOE T25 - Pumila - planta/18 | M26: ='Закупка'!V26 -> KAL-P KALANCHOE PUMILA T-25 planta, KCALT
A27: ='Закупка'!A27 -> 1.24 | B27: ='Закупка'!B27 -> EUPHORBIA TRIGONA | C27: ='Закупка'!R27 | D27: {=INDEX('Закупка'!G27:K27, $A$2)} -> 10 | E27: ='Закупка'!F27 -> 1 | F27: =IF(D27<>"",D27*E27,) -> 10 | G27: 10 | H27: 10 | K27: ='Закупка'!T27 -> 8400556 | L27: ='Закупка'!U27 -> EUPHORBIA 30cm -Milii - planta/22 | M27: ='Закупка'!V27 -> 174581, EUV
A28: ='Закупка'!A28 -> 1.25 | B28: ='Закупка'!B28 -> PTPB6537 ARRANGEMENTEN PASEN | C28: ='Закупка'!R28 | D28: {=INDEX('Закупка'!G28:K28, $A$2)} -> 1 | E28: ='Закупка'!F28 -> 1 | F28: =IF(D28<>"",D28*E28,) -> 1 | G28: 1 | H28: 1 | K28: ='Закупка'!T28 -> 84001153 | L28: ='Закупка'!U28 -> ARRANGEMENT DE PHALAENOPSIS - composición/56 | M28: ='Закупка'!V28
A29: ='Закупка'!A29 -> 1.26 | B29: ='Закупка'!B29 -> PTPB6525 ARRANGEMENTEN PASEN | C29: ='Закупка'!R29 | D29: {=INDEX('Закупка'!G29:K29, $A$2)} -> 1 | E29: ='Закупка'!F29 -> 1 | F29: =IF(D29<>"",D29*E29,) -> 1 | G29: 1 | H29: 1 | K29: ='Закупка'!T29 -> 84001153 | L29: ='Закупка'!U29 -> ARRANGEMENT DE PHALAENOPSIS - composición/56 | M29: ='Закупка'!V29
A30: ='Закупка'!A30 -> 1.27 | B30: ='Закупка'!B30 -> PHALAENOPSIS OTHER YELLOW | C30: ='Закупка'!R30 | D30: {=INDEX('Закупка'!G30:K30, $A$2)} | E30: ='Закупка'!F30 -> 1 | F30: =IF(D30<>"",D30*E30,) | K30: ='Закупка'!T30 -> 8400391 | L30: ='Закупка'!U30 -> PHALAENOPSIS MIX - planta/28 | M30: ='Закупка'!V30 -> 161202, 179376, 144102, 179304, 191963, 135419, 182797, 127000, 191284
A31: ='Закупка'!A31 -> 1.28 | B31: ='Закупка'!B31 -> SUCCULENTEN OTHER | C31: ='Закупка'!R31 | D31: {=INDEX('Закупка'!G31:K31, $A$2)} -> 3 | E31: ='Закупка'!F31 -> 1 | F31: =IF(D31<>"",D31*E31,) -> 3 | G31: 3 | H31: 3 | K31: ='Закупка'!T31 -> 8400591 | L31: ='Закупка'!U31 -> SUCCULENTUS OTHER - planta/28 | M31: ='Закупка'!V31 -> CRASSCI-9, AEON.012
A32: ='Закупка'!A32 -> 1.29 | B32: ='Закупка'!B32 -> RHIPSALIS MIX | C32: ='Закупка'!R32 | D32: {=INDEX('Закупка'!G32:K32, $A$2)} -> 12 | E32: ='Закупка'!F32 -> 1 | F32: =IF(D32<>"",D32*E32,) -> 12 | G32: 12 | H32: 12 | K32: ='Закупка'!T32 -> 8400895 | L32: ='Закупка'!U32 -> RHIPSALIS MIX - T17 planta colganta | M32: ='Закупка'!V32 -> 83612
A33: ='Закупка'!A33 | B33: ='Закупка'!B33 | C33: ='Закупка'!R33 | D33: {=INDEX('Закупка'!G33:K33, $A$2)} | E33: ='Закупка'!F33 | F33: =IF(D33<>"",D33*E33,) | K33: ='Закупка'!T33 | L33: ='Закупка'!U33 | M33: ='Закупка'!V33
A34: ='Закупка'!A34 | B34: ='Закупка'!B34 | C34: ='Закупка'!R34 | D34: {=INDEX('Закупка'!G34:K34, $A$2)} | E34: ='Закупка'!F34 | F34: =IF(D34<>"",D34*E34,) | K34: ='Закупка'!T34 | L34: ='Закупка'!U34 | M34: ='Закупка'!V34
A35: ='Закупка'!A35 | B35: ='Закупка'!B35 | C35: ='Закупка'!R35 | D35: {=INDEX('Закупка'!G35:K35, $A$2)} | E35: ='Закупка'!F35 | F35: =IF(D35<>"",D35*E35,) | K35: ='Закупка'!T35 | L35: ='Закупка'!U35 | M35: ='Закупка'!V35
A36: ='Закупка'!A36 | B36: ='Закупка'!B36 | C36: ='Закупка'!R36 | D36: {=INDEX('Закупка'!G36:K36, $A$2)} | E36: ='Закупка'!F36 | F36: =IF(D36<>"",D36*E36,) | K36: ='Закупка'!T36 | L36: ='Закупка'!U36 | M36: ='Закупка'!V36
A37: ='Закупка'!A37 | B37: ='Закупка'!B37 | C37: ='Закупка'!R37 | D37: {=INDEX('Закупка'!G37:K37, $A$2)} | E37: ='Закупка'!F37 | F37: =IF(D37<>"",D37*E37,) | K37: ='Закупка'!T37 | L37: ='Закупка'!U37 | M37: ='Закупка'!V37
A38: ='Закупка'!A38 | B38: ='Закупка'!B38 | C38: ='Закупка'!R38 | D38: {=INDEX('Закупка'!G38:K38, $A$2)} | E38: ='Закупка'!F38 | F38: =IF(D38<>"",D38*E38,) | K38: ='Закупка'!T38 | L38: ='Закупка'!U38 | M38: ='Закупка'!V38
A39: ='Закупка'!A39 | B39: ='Закупка'!B39 | C39: ='Закупка'!R39 | D39: {=INDEX('Закупка'!G39:K39, $A$2)} | E39: ='Закупка'!F39 | F39: =IF(D39<>"",D39*E39,) | K39: ='Закупка'!T39 | L39: ='Закупка'!U39 | M39: ='Закупка'!V39
A40: ='Закупка'!A40 | B40: ='Закупка'!B40 | C40: ='Закупка'!R40 | D40: {=INDEX('Закупка'!G40:K40, $A$2)} | E40: ='Закупка'!F40 | F40: =IF(D40<>"",D40*E40,) | K40: ='Закупка'!T40 | L40: ='Закупка'!U40 | M40: ='Закупка'!V40
A41: ='Закупка'!A41 | B41: ='Закупка'!B41 | C41: ='Закупка'!R41 | D41: {=INDEX('Закупка'!G41:K41, $A$2)} | E41: ='Закупка'!F41 | F41: =IF(D41<>"",D41*E41,) | K41: ='Закупка'!T41 | L41: ='Закупка'!U41 | M41: ='Закупка'!V41
A42: ='Закупка'!A42 | B42: ='Закупка'!B42 | C42: ='Закупка'!R42 | D42: {=INDEX('Закупка'!G42:K42, $A$2)} | E42: ='Закупка'!F42 | F42: =IF(D42<>"",D42*E42,) | K42: ='Закупка'!T42 | L42: ='Закупка'!U42 | M42: ='Закупка'!V42
A43: ='Закупка'!A43 | B43: ='Закупка'!B43 | C43: ='Закупка'!R43 | D43: {=INDEX('Закупка'!G43:K43, $A$2)} | E43: ='Закупка'!F43 | F43: =IF(D43<>"",D43*E43,) | K43: ='Закупка'!T43 | L43: ='Закупка'!U43 | M43: ='Закупка'!V43
A44: ='Закупка'!A44 | B44: ='Закупка'!B44 | C44: ='Закупка'!R44 | D44: {=INDEX('Закупка'!G44:K44, $A$2)} | E44: ='Закупка'!F44 | F44: =IF(D44<>"",D44*E44,) | K44: ='Закупка'!T44 | L44: ='Закупка'!U44 | M44: ='Закупка'!V44
... A146: ='Закупка'!A146 | B146: ='Закупка'!B146 | C146: ='Закупка'!R146 | D146: {=INDEX('Закупка'!G146:K146, $A$2)} | E146: ='Закупка'!F146 | F146: =IF(D146<>"",D146*E146,) | K146: ='Закупка'!T146 | L146: ='Закупка'!U146 | M146: ='Закупка'!V146
A147: ='Закупка'!A147 | B147: ='Закупка'!B147 | C147: ='Закупка'!R147 | D147: {=INDEX('Закупка'!G147:K147, $A$2)} | E147: ='Закупка'!F147 | F147: =IF(D147<>"",D147*E147,) | J147: =IF(H147<>"", H147-F147,) | K147: ='Закупка'!T147 | L147: ='Закупка'!U147 | M147: ='Закупка'!V147
A148: ='Закупка'!A148 | B148: ='Закупка'!B148 | C148: ='Закупка'!R148 | D148: {=INDEX('Закупка'!G148:K148, $A$2)} | E148: ='Закупка'!F148 | F148: =IF(D148<>"",D148*E148,) | J148: =IF(H148<>"", H148-F148,) | K148: ='Закупка'!T148 | L148: ='Закупка'!U148 | M148: ='Закупка'!V148
A149: ='Закупка'!A149 | B149: ='Закупка'!B149 | C149: ='Закупка'!R149 | D149: {=INDEX('Закупка'!G149:K149, $A$2)} | E149: ='Закупка'!F149 | F149: =IF(D149<>"",D149*E149,) | J149: =IF(H149<>"", H149-F149,) | K149: ='Закупка'!T149 | L149: ='Закупка'!U149 | M149: ='Закупка'!V149
A150: ='Закупка'!A150 | B150: ='Закупка'!B150 | C150: ='Закупка'!R150 | D150: {=INDEX('Закупка'!G150:K150, $A$2)} | E150: ='Закупка'!F150 | F150: =IF(D150<>"",D150*E150,) | J150: =IF(H150<>"", H150-F150,) | K150: ='Закупка'!T150 | L150: ='Закупка'!U150 | M150: ='Закупка'!V150
A151: ='Закупка'!A151 | B151: ='Закупка'!B151 | C151: ='Закупка'!R151 | D151: {=INDEX('Закупка'!G151:K151, $A$2)} | E151: ='Закупка'!F151 | F151: =IF(D151<>"",D151*E151,) | J151: =IF(H151<>"", H151-F151,) | K151: ='Закупка'!T151 | L151: ='Закупка'!U151 | M151: ='Закупка'!V151
A152: ='Закупка'!A152 | B152: ='Закупка'!B152 | C152: ='Закупка'!R152 | D152: {=INDEX('Закупка'!G152:K152, $A$2)} | E152: ='Закупка'!F152 | F152: =IF(D152<>"",D152*E152,) | J152: =IF(H152<>"", H152-F152,) | K152: ='Закупка'!T152 | L152: ='Закупка'!U152 | M152: ='Закупка'!V152
A153: ='Закупка'!A153 | B153: ='Закупка'!B153 | C153: ='Закупка'!R153 | D153: {=INDEX('Закупка'!G153:K153, $A$2)} | E153: ='Закупка'!F153 | F153: =IF(D153<>"",D153*E153,) | J153: =IF(H153<>"", H153-F153,) | K153: ='Закупка'!T153 | L153: ='Закупка'!U153 | M153: ='Закупка'!V153
A154: ='Закупка'!A154 | B154: ='Закупка'!B154 | C154: ='Закупка'!R154 | D154: {=INDEX('Закупка'!G154:K154, $A$2)} | E154: ='Закупка'!F154 | F154: =IF(D154<>"",D154*E154,) | J154: =IF(H154<>"", H154-F154,) | K154: ='Закупка'!T154 | L154: ='Закупка'!U154 | M154: ='Закупка'!V154
A155: ='Закупка'!A155 | B155: ='Закупка'!B155 | C155: ='Закупка'!R155 | D155: {=INDEX('Закупка'!G155:K155, $A$2)} | E155: ='Закупка'!F155 | F155: =IF(D155<>"",D155*E155,) | J155: =IF(H155<>"", H155-F155,) | K155: ='Закупка'!T155 | L155: ='Закупка'!U155 | M155: ='Закупка'!V155
A156: ='Закупка'!A156 | B156: ='Закупка'!B156 | C156: ='Закупка'!R156 | D156: {=INDEX('Закупка'!G156:K156, $A$2)} | E156: ='Закупка'!F156 | F156: =IF(D156<>"",D156*E156,) | J156: =IF(H156<>"", H156-F156,) | K156: ='Закупка'!T156 | L156: ='Закупка'!U156 | M156: ='Закупка'!V156
A157: ='Закупка'!A157 | B157: ='Закупка'!B157 | C157: ='Закупка'!R157 | D157: {=INDEX('Закупка'!G157:K157, $A$2)} | E157: ='Закупка'!F157 | F157: =IF(D157<>"",D157*E157,) | J157: =IF(H157<>"", H157-F157,) | K157: ='Закупка'!T157 | L157: ='Закупка'!U157 | M157: ='Закупка'!V157
A158: ='Закупка'!A158 | B158: ='Закупка'!B158 | C158: ='Закупка'!R158 | D158: {=INDEX('Закупка'!G158:K158, $A$2)} | E158: ='Закупка'!F158 | F158: =IF(D158<>"",D158*E158,) | J158: =IF(H158<>"", H158-F158,) | K158: ='Закупка'!T158 | L158: ='Закупка'!U158 | M158: ='Закупка'!V158
... A199: ='Закупка'!A199 | B199: ='Закупка'!B199 | C199: ='Закупка'!R199 | D199: {=INDEX('Закупка'!G199:K199, $A$2)} | E199: ='Закупка'!F199 | F199: =IF(D199<>"",D199*E199,) | J199: =IF(H199<>"", H199-F199,) | K199: ='Закупка'!T199 | L199: ='Закупка'!U199 | M199: ='Закупка'!V199

Sheet Результат
B1: 45736 | C1: брак возврат | D1: M | G1: P | J1: A | M1: G | P1: B | S1: ПАЧКИ | V1: ШТУКИ | X1: факутру перенесли в HOLDED | Y1: ЦЕНЫ | AA1: HOLDED
B2: комментарий логиста? как в накладной? | D2: > | E2: < | F2: штуки | G2: > | H2: < | I2: штуки | J2: > | K2: < | L2: штуки | M2: > | N2: < | O2: штуки | P2: > | Q2: < | R2: штуки | S2: купили | T2: получили везде | U2: внтури пачки штук? | V2: ожидали | W2: реально посчитали везде | Y2: новая цена | Z2: цена в базе | AA2: фото | AB2: Holded артикул | AC2: название с поиском | AD2: img
A3: ='Закупка'!A3 | B3: ='Закупка'!B3 -> Фактура 1 | C3: ='Закупка'!L3 | D3: ='Закупка'!G3 | E3: =Muntaner!G3 | F3: =Muntaner!H3 | G3: ='Закупка'!H3 | H3: =Plaza!G3 | I3: =Plaza!H3 | J3: ='Закупка'!I3 | K3: =Augusta!G3 | L3: =Augusta!H3 | M3: ='Закупка'!J3 | N3: =Gloria!G3 | O3: =Gloria!H3 | P3: ='Закупка'!K3 | Q3: =Blau!G3 | R3: =Blau!H3 | S3: ='Закупка'!E3 | T3: =IF(E3+H3+K3+N3+Q3=0, "", E3+H3+K3+N3+Q3) | U3: ='Закупка'!F3 | V3: ='Закупка'!O3 | W3: =IF(F3+I3+L3+O3+R3=0, "", F3+I3+L3+O3+R3) | Y3: ='Закупка'!P3 | Z3: ='Закупка'!Q3 | AA3: ='Закупка'!R3 | AB3: ='Закупка'!T3 | AC3: ='Закупка'!S3 | AD3: ='Закупка'!W3 | AE3: ='Закупка'!Y3
A4: ='Закупка'!A4 -> 1.1 | B4: ='Закупка'!B4 -> RANUNCULUS CLOONEY TUAREQ | C4: ='Закупка'!L4 | D4: ='Закупка'!G4 | E4: =Muntaner!G4 | F4: =Muntaner!H4 | G4: ='Закупка'!H4 | H4: =Plaza!G4 | I4: =Plaza!H4 | J4: ='Закупка'!I4 | K4: =Augusta!G4 | L4: =Augusta!H4 | M4: ='Закупка'!J4 -> 3 | N4: =Gloria!G4 -> 3 | O4: =Gloria!H4 -> 30 | P4: ='Закупка'!K4 | Q4: =Blau!G4 | R4: =Blau!H4 | S4: ='Закупка'!E4 -> 3 | T4: =IF(E4+H4+K4+N4+Q4=0, "", E4+H4+K4+N4+Q4) -> 3 | U4: ='Закупка'!F4 -> 10 | V4: ='Закупка'!O4 -> 30 | W4: =IF(F4+I4+L4+O4+R4=0, "", F4+I4+L4+O4+R4) -> 30 | Y4: ='Закупка'!P4 -> 3 | Z4: ='Закупка'!Q4 -> 2.999997 | AA4: ='Закупка'!R4 | AB4: ='Закупка'!T4 -> 8400518 | AC4: ='Закупка'!S4 -> 8400518 - RANUNCULUS - Butterfly - flor ( RANUBUBL, RANUBUSA, 174946, 147132, 126830) | AD4: ='Закупка'!W4 -> https://drive.google.com/uc?export=view&id=1mbmVjM82bGnM8nxdZnDYmJjSQLnHiol0 | AE4: ='Закупка'!Y4
A5: ='Закупка'!A5 -> 1.2 | B5: ='Закупка'!B5 -> RANUNCULUS CLOONEY GRAND PASTEL | C5: ='Закупка'!L5 | D5: ='Закупка'!G5 | E5: =Muntaner!G5 | F5: =Muntaner!H5 | G5: ='Закупка'!H5 | H5: =Plaza!G5 | I5: =Plaza!H5 | J5: ='Закупка'!I5 | K5: =Augusta!G5 | L5: =Augusta!H5 | M5: ='Закупка'!J5 | N5: =Gloria!G5 | O5: =Gloria!H5 | P5: ='Закупка'!K5 -> 6 | Q5: =Blau!G5 -> 6 | R5: =Blau!H5 -> 48 | S5: ='Закупка'!E5 -> 6 | T5: =IF(E5+H5+K5+N5+Q5=0, "", E5+H5+K5+N5+Q5) -> 6 | U5: ='Закупка'!F5 -> 10 | V5: ='Закупка'!O5 -> 60 | W5: =IF(F5+I5+L5+O5+R5=0, "", F5+I5+L5+O5+R5) -> 48 | Y5: ='Закупка'!P5 -> 3 | Z5: ='Закупка'!Q5 -> 2.999997 | AA5: ='Закупка'!R5 | AB5: ='Закупка'!T5 -> 8400518 | AC5: ='Закупка'!S5 -> 8400518 - RANUNCULUS - Butterfly - flor ( RANUBUBL, RANUBUSA, 174946, 147132, 126830) | AD5: ='Закупка'!W5 -> https://drive.google.com/uc?export=view&id=1mbmVjM82bGnM8nxdZnDYmJjSQLnHiol0 | AE5: ='Закупка'!Y5
A6: ='Закупка'!A6 -> 1.3 | B6: ='Закупка'!B6 -> ALSTROEMERIA SI SOFIENA | C6: ='Закупка'!L6 | D6: ='Закупка'!G6 | E6: =Muntaner!G6 | F6: =Muntaner!H6 | G6: ='Закупка'!H6 -> 2 | H6: =Plaza!G6 -> 2 | I6: =Plaza!H6 -> 20 | J6: ='Закупка'!I6 | K6: =Augusta!G6 | L6: =Augusta!H6 | M6: ='Закупка'!J6 -> 2 | N6: =Gloria!G6 -> 2 | O6: =Gloria!H6 -> 20 | P6: ='Закупка'!K6 -> 2 | Q6: =Blau!G6 -> 2 | R6: =Blau!H6 -> 18 | S6: ='Закупка'!E6 -> 6 | T6: =IF(E6+H6+K6+N6+Q6=0, "", E6+H6+K6+N6+Q6) -> 6 | U6: ='Закупка'!F6 -> 10 | V6: ='Закупка'!O6 -> 60 | W6: =IF(F6+I6+L6+O6+R6=0, "", F6+I6+L6+O6+R6) -> 58 | Y6: ='Закупка'!P6 | Z6: ='Закупка'!Q6 -> 2.999997 | AA6: ='Закупка'!R6 | AB6: ='Закупка'!T6 -> 8400154 | AC6: ='Закупка'!S6 -> 8400154 - ALSTROEMERIA - flor (00027, 11920, 146548, 148465, ALS VA, 148462, 148466, 11920, ALS-P, 137896, 137077, 137894, 148289, 148469, ALSTROEMERIES ALSTROEMERIA, ALSP, 11920) | AD6: ='Закупка'!W6 -> https://drive.google.com/uc?export=view&id=1hD_EIkM8w5p_WtnrcMdhYX6szEYoVelf | AE6: ='Закупка'!Y6
A7: ='Закупка'!A7 -> 1.4 | B7: ='Закупка'!B7 -> ROSA LARGE BELLE ROSE | C7: ='Закупка'!L7 | D7: ='Закупка'!G7 | E7: =Muntaner!G7 | F7: =Muntaner!H7 | G7: ='Закупка'!H7 | H7: =Plaza!G7 | I7: =Plaza!H7 | J7: ='Закупка'!I7 | K7: =Augusta!G7 | L7: =Augusta!H7 | M7: ='Закупка'!J7 | N7: =Gloria!G7 | O7: =Gloria!H7 | P7: ='Закупка'!K7 -> 6 | Q7: =Blau!G7 -> 6 | R7: =Blau!H7 -> 60 | S7: ='Закупка'!E7 -> 6 | T7: =IF(E7+H7+K7+N7+Q7=0, "", E7+H7+K7+N7+Q7) -> 6 | U7: ='Закупка'!F7 -> 10 | V7: ='Закупка'!O7 -> 60 | W7: =IF(F7+I7+L7+O7+R7=0, "", F7+I7+L7+O7+R7) -> 60 | Y7: ='Закупка'!P7 -> 2 | Z7: ='Закупка'!Q7 -> 1.999998 | AA7: ='Закупка'!R7 | AB7: ='Закупка'!T7 -> 8400731 | AC7: ='Закупка'!S7 -> 8400731 - RS ROSA LA BELLE LOLOMARIK - flor (181496) | AD7: ='Закупка'!W7 -> https://drive.google.com/uc?export=view&id=1fUhUDsiSHWrleyP7h5w_2pEpagbWza0G | AE7: ='Закупка'!Y7
A8: ='Закупка'!A8 -> 1.5 | B8: ='Закупка'!B8 -> ROSA GARDEN PRISCILLA! | C8: ='Закупка'!L8 | D8: ='Закупка'!G8 | E8: =Muntaner!G8 | F8: =Muntaner!H8 | G8: ='Закупка'!H8 | H8: =Plaza!G8 | I8: =Plaza!H8 | J8: ='Закупка'!I8 | K8: =Augusta!G8 | L8: =Augusta!H8 | M8: ='Закупка'!J8 -> 2 | N8: =Gloria!G8 -> 2 | O8: =Gloria!H8 -> 10 | P8: ='Закупка'!K8 -> 4 | Q8: =Blau!G8 -> 4 | R8: =Blau!H8 -> 20 | S8: ='Закупка'!E8 -> 6 | T8: =IF(E8+H8+K8+N8+Q8=0, "", E8+H8+K8+N8+Q8) -> 6 | U8: ='Закупка'!F8 -> 5 | V8: ='Закупка'!O8 -> 30 | W8: =IF(F8+I8+L8+O8+R8=0, "", F8+I8+L8+O8+R8) -> 30 | Y8: ='Закупка'!P8 | Z8: ='Закупка'!Q8 -> 2.999997 | AA8: ='Закупка'!R8 | AB8: ='Закупка'!T8 -> 84001081 | AC8: ='Закупка'!S8 -> 84001081 - ROSA PRISCILLA - flor () | AD8: ='Закупка'!W8 -> https://drive.google.com/uc?export=view&id=1dI4YSHY8sPn-AzvYOdjKrrjGMV26hEE0 | AE8: ='Закупка'!Y8
A9: ='Закупка'!A9 -> 1.6 | B9: ='Закупка'!B9 -> ROSA GARDEN MIX UHURU | C9: ='Закупка'!L9 | D9: ='Закупка'!G9 | E9: =Muntaner!G9 | F9: =Muntaner!H9 | G9: ='Закупка'!H9 | H9: =Plaza!G9 | I9: =Plaza!H9 | J9: ='Закупка'!I9 | K9: =Augusta!G9 | L9: =Augusta!H9 | M9: ='Закупка'!J9 | N9: =Gloria!G9 | O9: =Gloria!H9 | P9: ='Закупка'!K9 -> 8 | Q9: =Blau!G9 -> 8 | R9: =Blau!H9 -> 46 | S9: ='Закупка'!E9 -> 8 | T9: =IF(E9+H9+K9+N9+Q9=0, "", E9+H9+K9+N9+Q9) -> 8 | U9: ='Закупка'!F9 -> 6 | V9: ='Закупка'!O9 -> 48 | W9: =IF(F9+I9+L9+O9+R9=0, "", F9+I9+L9+O9+R9) -> 46 | Y9: ='Закупка'!P9 -> 3 | Z9: ='Закупка'!Q9 | AA9: ='Закупка'!R9 | AB9: ='Закупка'!T9 -> 84001157 | AC9: ='Закупка'!S9 -> 84001157 - RISA GARDAN MIX - flor/3 () | AD9: ='Закупка'!W9 -> ❗Ошибка: application/json | AE9: ='Закупка'!Y9
A10: ='Закупка'!A10 -> 1.7 | B10: ='Закупка'!B10 -> ROSA SPRAY CHIMO | C10: ='Закупка'!L10 | D10: ='Закупка'!G10 | E10: =Muntaner!G10 | F10: =Muntaner!H10 | G10: ='Закупка'!H10 -> 2 | H10: =Plaza!G10 -> 2 | I10: =Plaza!H10 -> 20 | J10: ='Закупка'!I10 | K10: =Augusta!G10 | L10: =Augusta!H10 | M10: ='Закупка'!J10 -> 3 | N10: =Gloria!G10 -> 3 | O10: =Gloria!H10 -> 30 | P10: ='Закупка'!K10 -> 3 | Q10: =Blau!G10 -> 3 | R10: =Blau!H10 -> 30 | S10: ='Закупка'!E10 -> 8 | T10: =IF(E10+H10+K10+N10+Q10=0, "", E10+H10+K10+N10+Q10) -> 8 | U10: ='Закупка'!F10 -> 10 | V10: ='Закупка'!O10 -> 80 | W10: =IF(F10+I10+L10+O10+R10=0, "", F10+I10+L10+O10+R10) -> 80 | Y10: ='Закупка'!P10 | Z10: ='Закупка'!Q10 -> 2.999997 | AA10: ='Закупка'!R10 | AB10: ='Закупка'!T10 -> 8400828 | AC10: ='Закупка'!S10 -> 8400828 - ROSA CHIMO - flor (135409) | AD10: ='Закупка'!W10 -> https://drive.google.com/uc?export=view&id=14lKbr1IZa_y54C-n_irMTGAXEPdZJoIn | AE10: ='Закупка'!Y10
A11: ='Закупка'!A11 -> 1.8 | B11: ='Закупка'!B11 -> ROSA SPRAY BIRDS NEST+ | C11: ='Закупка'!L11 | D11: ='Закупка'!G11 | E11: =Muntaner!G11 | F11: =Muntaner!H11 | G11: ='Закупка'!H11 | H11: =Plaza!G11 | I11: =Plaza!H11 | J11: ='Закупка'!I11 | K11: =Augusta!G11 | L11: =Augusta!H11 | M11: ='Закупка'!J11 -> 1 | N11: =Gloria!G11 -> 1 | O11: =Gloria!H11 -> 10 | P11: ='Закупка'!K11 -> 3 | Q11: =Blau!G11 -> 3 | R11: =Blau!H11 -> 30 | S11: ='Закупка'!E11 -> 4 | T11: =IF(E11+H11+K11+N11+Q11=0, "", E11+H11+K11+N11+Q11) -> 4 | U11: ='Закупка'!F11 -> 10 | V11: ='Закупка'!O11 -> 40 | W11: =IF(F11+I11+L11+O11+R11=0, "", F11+I11+L11+O11+R11) -> 40 | Y11: ='Закупка'!P11 -> 4 | Z11: ='Закупка'!Q11 -> 3.999996 | AA11: ='Закупка'!R11 | AB11: ='Закупка'!T11 -> 84001078 | AC11: ='Закупка'!S11 -> 84001078 - ROSA BIRDS NEST - flor () | AD11: ='Закупка'!W11 -> https://drive.google.com/uc?export=view&id=1cMWmYq9Ijr9CTBLT1xhfRb5ZQ_GrN7hE | AE11: ='Закупка'!Y11
A12: ='Закупка'!A12 -> 1.9 | B12: ='Закупка'!B12 -> ROSA LARGE CELEB | C12: ='Закупка'!L12 | D12: ='Закупка'!G12 | E12: =Muntaner!G12 | F12: =Muntaner!H12 | G12: ='Закупка'!H12 -> 3 | H12: =Plaza!G12 -> 3 | I12: =Plaza!H12 -> 30 | J12: ='Закупка'!I12 | K12: =Augusta!G12 | L12: =Augusta!H12 | M12: ='Закупка'!J12 -> 3 | N12: =Gloria!G12 -> 3 | O12: =Gloria!H12 -> 28 | P12: ='Закупка'!K12 | Q12: =Blau!G12 | R12: =Blau!H12 | S12: ='Закупка'!E12 -> 6 | T12: =IF(E12+H12+K12+N12+Q12=0, "", E12+H12+K12+N12+Q12) -> 6 | U12: ='Закупка'!F12 -> 10 | V12: ='Закупка'!O12 -> 60 | W12: =IF(F12+I12+L12+O12+R12=0, "", F12+I12+L12+O12+R12) -> 58 | Y12: ='Закупка'!P12 -> 3 | Z12: ='Закупка'!Q12 -> 2.999997 | AA12: ='Закупка'!R12 | AB12: ='Закупка'!T12 -> 84001044 | AC12: ='Закупка'!S12 -> 84001044 - ROSA CELEBRATING HEATHER - flor () | AD12: ='Закупка'!W12 -> https://drive.google.com/uc?export=view&id=14z6focMNsmhbYM377L2M-B88nBfvXnJJ | AE12: ='Закупка'!Y12
A13: ='Закупка'!A13 -> 1.10 | B13: ='Закупка'!B13 -> ARR CACTUS | C13: ='Закупка'!L13 | D13: ='Закупка'!G13 | E13: =Muntaner!G13 | F13: =Muntaner!H13 | G13: ='Закупка'!H13 | H13: =Plaza!G13 | I13: =Plaza!H13 | J13: ='Закупка'!I13 | K13: =Augusta!G13 | L13: =Augusta!H13 | M13: ='Закупка'!J13 -> 9 | N13: =Gloria!G13 -> 1 | O13: =Gloria!H13 -> 9 | P13: ='Закупка'!K13 -> 9 | Q13: =Blau!G13 -> 9 | R13: =Blau!H13 -> 9 | S13: ='Закупка'!E13 -> 18 | T13: =IF(E13+H13+K13+N13+Q13=0, "", E13+H13+K13+N13+Q13) -> 10 | U13: ='Закупка'!F13 -> 1 | V13: ='Закупка'!O13 -> 18 | W13: =IF(F13+I13+L13+O13+R13=0, "", F13+I13+L13+O13+R13) -> 18 | Y13: ='Закупка'!P13 -> 22 | Z13: ='Закупка'!Q13 -> 22 | AA13: ='Закупка'!R13 | AB13: ='Закупка'!T13 -> 8400594 | AC13: ='Закупка'!S13 -> 8400594 - CACTUS - planta/22 (TEST 13 cactus) | AD13: ='Закупка'!W13 -> https://drive.google.com/uc?export=view&id=1Q-AyZHgyh6uUyL-RDutGOkXSIkuILjHz | AE13: ='Закупка'!Y13
A14: ='Закупка'!A14 -> 1.11 | B14: ='Закупка'!B14 -> ALOE ARBO | C14: ='Закупка'!L14 | D14: ='Закупка'!G14 | E14: =Muntaner!G14 | F14: =Muntaner!H14 | G14: ='Закупка'!H14 | H14: =Plaza!G14 | I14: =Plaza!H14 | J14: ='Закупка'!I14 | K14: =Augusta!G14 | L14: =Augusta!H14 | M14: ='Закупка'!J14 -> 1 | N14: =Gloria!G14 -> 1 | O14: =Gloria!H14 -> 1 | P14: ='Закупка'!K14 | Q14: =Blau!G14 | R14: =Blau!H14 | S14: ='Закупка'!E14 -> 1 | T14: =IF(E14+H14+K14+N14+Q14=0, "", E14+H14+K14+N14+Q14) -> 1 | U14: ='Закупка'!F14 -> 1 | V14: ='Закупка'!O14 -> 1 | W14: =IF(F14+I14+L14+O14+R14=0, "", F14+I14+L14+O14+R14) -> 1 | Y14: ='Закупка'!P14 -> 67 | Z14: ='Закупка'!Q14 -> 66.999999 | AA14: ='Закупка'!R14 | AB14: ='Закупка'!T14 -> 84001156 | AC14: ='Закупка'!S14 -> 84001156 - ALOE ARBO - planta/67 () | AD14: ='Закупка'!W14 -> https://drive.google.com/uc?export=view&id=1nhRiZiSymvZqgrwdzMgNfzK5d8VGqcGQ | AE14: ='Закупка'!Y14
... A193: ='Закупка'!A193 | B193: ='Закупка'!B193 | C193: ='Закупка'!L193 | D193: ='Закупка'!G193 | E193: =Muntaner!G193 | F193: =Muntaner!H193 | G193: ='Закупка'!H193 | H193: =Plaza!G193 | I193: =Plaza!H193 | J193: ='Закупка'!I193 | K193: =Augusta!G193 | L193: =Augusta!H193 | M193: ='Закупка'!J193 | N193: =Gloria!G193 | O193: =Gloria!H193 | P193: ='Закупка'!K193 | Q193: =Blau!G193 | R193: =Blau!H193 | S193: ='Закупка'!E193 | T193: =IF(E193+H193+K193+N193+Q193=0, "", E193+H193+K193+N193+Q193) | U193: ='Закупка'!F193 | V193: ='Закупка'!O193 | W193: =IF(F193+I193+L193+O193+R193=0, "", F193+I193+L193+O193+R193) | Y193: ='Закупка'!P193 | Z193: ='Закупка'!Q193 | AA193: ='Закупка'!R193 | AB193: ='Закупка'!T193 | AC193: ='Закупка'!S193 | AD193: ='Закупка'!W193 | AE193: ='Закупка'!Y193

Sheet Инструкция
B4: План закупок
B5: 1. Покупаем товар, берем фактуру. Ставим на ней порядоковый номер за день (в кружочке по центру вверху) и нумеруем все позиции
B6: 2. фото факутры в Логисты
B7: 2.1 закрываем цены фото накладной в ЗАКУПКИ товара и туда же фото товара подписываем номер фактры точка номер позиции например 3.2
B8: 3. вносим в ведомость номер фактуры, номер товара, краткое название и артикул продавца (как хочется) - и сколько всего купили
B9: 4. сразу же пишем куда распределяем по магазинам
B13: Бек офис
B14: 1. вписывает все известные артикулы в систему
B15: 2. Неизвестные спрашивает у логиста если надо создает новые карточки
B16: 2.2 красивое фото карточек просит сделать филиал в их группе
B17: 3 проверяет изменение цен
B18: 3.1. то что сразу сказал логист
... B24: 1. заполняют акт по накладной в своей папке

Sheet products
A1: Product ID | B1: SKU | C1: Nombre | F1: Código de fábrica
A2: 67a397d0d3f7c54b2c00dd8b | B2: 8400916 | C2: CILINDRO CRISTAL 155XH350MM | F2: YE6000760
A3: 6798e60810946ac55101581d | B3: R00038 | C3: MARCADOR | F3: rotulador
A4: 6798e5b55aa428f092028194 | B4: R00037 | C4: BOLIGRAFO
A5: 6798e5228e08ea0b190a75bf | B5: R00036 | C5: TRAPO PARA FREGONA
A6: 6798e4a511a9d29d6f0a44e9 | B6: R00035 | C6: ESPONJA PARA LAVAR
A7: 6798e345728a2c96600b4901 | B7: R00034 | C7: BOLSAS DE BASURA
A8: 6798e2ed2c73d8973e084548 | B8: R00033 | C8: LIMPIACRISTALES
A9: 6798e26530bae3b3e20e44bb | B9: R00032 | C9: LIMPIADOR DE SUELOS
A10: 6798e1e33b01d2095f0a52c1 | B10: R00031 | C10: BAYETA DE LIMPIEZA
A11: 6798e11e36e153e1c90b9b71 | B11: R00030 | C11: GUANTES FLORISTICOS
A12: 6798e05464ae6abe870282e8 | B12: R00029 | C12: TOALLA DE PAPEL
A13: 67781cc6a8ab4e31b00a3b89 | B13: R00028 | C13: BOLSA ARAIK TAMAÑO XL | F13: 6050 8400274 8050503522105
A14: 67781a9dfb31216da1064f2e | B14: R00027 | C14: BOLSA ARAIK TAMAÑO M | F14: 6106 8400273
A15: 67781e0d6c7befe3d307b4d3 | B15: R00026 | C15: BOLSA ARAIK TAMAÑO S | F15: 2623
A16: 6798dc94824c3e36c1016596 | B16: R00025 | C16: Albaran de traslado de mercancias | F16: Albaran de traslado de mercancias
A17: 6798dbca8236d5a68a07efab | B17: R00024 | C17: Acta de recepcion de mercancia | F17: Acta de recepcion de mercancia
A18: 6798d9b06b7c8765e9006733 | B18: R00023 | C18: Etiquetas adhesivas (impresora de precios) | F18: Etiquetas adhesivas
A19: 673c901c2f96c98c700f48c5 | B19: R00022 | C19: CUCHILLO FLORISTA 1UND | F19: 5024242421459, 1987-16
A20: 673c91136cb13b6f1405044d | B20: R00021 | C20: TIJERAS DE PODAR | F20: 8422347199018, 80523360176, 4000510982830, secadores, 32-00011
A21: 6703dd70d0d4310e8f0af140 | B21: R00020 | C21: TIJERAS FLORES | F21: 8719202891010, 5024242421527, 8410990001284
A22: 672c8e0fd6c084279b031cf8 | B22: R00019 | C22: ADHESIVO DE SILICONA 1KG OASIS | F22: 5024242663071 ADHESIVO DE SILICONA 1KG OASIS
A23: 6703dc92bd2e45464000f3d2 | B23: R00018 | C23: PISTOLA SILICONA 80W OASIS | F23: 4000510929200 PISTOLA SILICONA 80W OASIS
A24: 6798d205d8356889ed0b3607 | B24: R00017 | C24: PALITOS DE BAMBU
A25: 6798d0f3e0446df5880375a6 | B25: R00016 | C25: CINTA ADHESIVA NEGRA | F25: CINTA ADHESIVA NEGRA
A26: 673f596d8816b03a3801eac7 | B26: R00015 | C26: Hilo negro para etiquetas | F26: 8436036131531, 8436548911973
A27: 677eb58111dfddbee20bc222 | B27: R00014 | C27: CINTA ORGANZA | F27: CINTA ORGANZA, 2716
A28: 6703df5376586e9b5b03a58a | B28: R00013 | C28: CELOFAN BLANCO MATE | F28: 8434329000038, 09001735070050
A29: 676ec6339c087d28580805e5 | B29: R00012 | C29: CELOFAN NEGRO OPACO | F29: 34224323070025
A30: 675c597b32e0808baf0bbbb8 | B30: R00011 | C30: Etiquetas de marca Araik Galstyan | F30: 8400224 Etiquetas de marca Araik Galstyan
A31: 673c932cf25d73aa020dee6f | B31: R00010 | C31: PULVERIZADOR 1L | F31: 8711295692222 PULVERIZADOR 1L
A32: 672c909e82bb45ce870dd345 | B32: R00009 | C32: OASIS ESPONJA FLORAL 1 und | F32: 4000510010106, 10-01010, 1002002, 5104
A33: 677d50f6c61cb92f6301222e | B33: R00008 | C33: Papel térmico en rollo (terminal) | F33: Papel para terminal
A34: 677d4819ca31ed30a40b3633 | B34: R00006 | C34: Papel blanco en rollo Fernando | F34: PP05 Papel blanco en rollo Fernando
A35: 677d47a91185280a01074be8 | B35: R00005 | C35: Papel transparente en rollo | F35: 70050 Papel transparente en rollo
A36: 677d4736b00df30d300b2fbd | B36: R00004 | C36: Papel blanco, negro en rollo | F36: 491901 Papel blanco en rollo
... A41: 674745574850d2532c045367 | B41: R00039 | C41: CUBO NEGRO REDONDO DE PLASTICO | F41: 14109, 14110
A42: 6703d9ff85b5026c480985b4 | B42: 8400007 | C42: CESTA MIMBRE GRANDE
A43: 67b7403bb74ded87830b1147 | B43: 8400459 | C43: [closed] ALMENDRA con FLORES 1,5-2m - rama | F43: 8400459
A44: 67b7340037e697e3f60a0854 | B44: 8400458 | C44: HELECHO T10 - planta/14 | F44: 8400458
A45: 67b73346be2f0d7edf0e7e40 | B45: 8400457 | C45: HORTENSIA T14, T15 - planta/28 | F45: HOR, 130498, 99757, 130498, 175237, 176490,10104, 172749
A46: 67b71d34a6c37dd24b09ae39 | B46: 8400456 | C46: ROSA - Mondial | F46: RSC60 8400456, 177325, 177160, 177161, 177161
A47: 67b46aeefd3021d1ec0140f9 | B47: 8400455 | C47: CALA MIX - planta/20 | F47: Cala 8400455, 95, 1035, 193945
A48: 67b467df3a4878b4b209d5dc | B48: 8400454 | C48: YUCCA 120cm - planta/165 | F48: YUCCA 120cm planta
A49: 67b464d2fb7efe39e304ff1a | B49: 8400453 | C49: YUCCA 90cm - planta/135 | F49: YUCCA 90cm planta
A50: 67b45ac08ba2ed54050a09a4 | B50: 8400452 | C50: FICUS T20 - Benjamina - planta/35 | F50: FICBEN20PAC FICUS BENJAMINA T-20 planta
A51: 67b456f2b3fc708ef80cb321 | B51: 8400451 | C51: DRACAENA T5L- Compacta - planta/42 | F51: dracaena DRACENA COMPACTA 5L planta
A52: 67b37be7118792857d01a74a | B52: 8400450 | C52: [closed] CALA T5L - planta/15 | F52: CA21 Calla Zantedeschia Aethiopica 5L planta
A53: 67b37902fb8dc102720afa33 | B53: 8400449 | C53: PHILODENDRON T14 - Birkin - planta/18 | F53: PHILB, 179578, WHITE, BIRKIN PHILODENDRON BIRKIN T-14 planta
A54: 67b3755f925e01531407d9a8 | B54: 8400448 | C54: KALANCHOE T25 - Pumila - planta/18 | F54: KAL-P KALANCHOE PUMILA T-25 planta, KCALT
... A227: 6776b16937a7ca9eb700c3b7 | B227: 8400257 | C227: [closed] CRISANTEMA UNIFLOR PLAYTIME - flor | F227: CRISUNHOPL CRISANTEMA UNIFLOR PLAYTIME
A228: 676ec1df79dbb8f9d705d8a4 | B228: 8400256 | C228: CILINDRO 18X18 CORTE
A229: 676ec187755190633c066609 | B229: 8400255 | C229: [closed] CILINDRO 40X15
A230: 6776adeffabeeca13209d291 | B230: 8400254 | C230: LIMONIUM - Konfeti Bola - flor | F230: LIMOKOFU, LIMOKOPOAM, 84451, CON, 76347, 27701, LIMONIUM, 62839
A231: 6776ad35663c38a4180ad04a | B231: 8400253 | C231: MARFULL - rama | F231: MARF, MAR, MADR 8400253, 110294, Photinia en Flor Paq, 175600, MADROÑO, ARBUTUS, MAD, MADROÑO
A232: 6776a518801ca5f9a1039313 | B232: 8400252 | C232: ALAMO - palo | F232: BETG ALAMOGR
A233: 676ee78b2c7cfbb80c0f64a6 | B233: 8400251 | C233: [deleted] Eucalipto Color
A234: 676eba469cd930208107d066 | B234: 8400250 | C234: [deleted] Magnolia hojas grandes | F234: MAGP MagnoliaG
A235: 676eb9f42d3e6c751606c082 | B235: 8400249 | C235: MAGNOLIA - MINI - rama | F235: MAGP Magnolia, 69031
A236: 676eb6aada8499a2c004dcba | B236: 8400248 | C236: [deleted] HORTENSIA (TALLO) | F236: HORT hortensia
A237: 676ea56d19e26084b8029f42 | B237: 8400247 | C237: [deleted] Leucodendron SAFARI SUNSET 50cm | F237: SAFASU50GR
A238: 676e9383a49fd556340de22e | B238: 8400246 | C238: GENISTA - MIX - rama | F238: GIN GINESTA, 143653, 144060, 77016,
A239: 676e9152ff73fbd3df099c46 | B239: 8400245 | C239: [closed] POETA - MIX -flor | F239: POE POETA
A240: 676ee2a4fed2160fe10601cc | B240: 8400244 | C240: [closed] CLAVEL - Colombiano - flor | F240: Clavel Colombiano
A241: 676585164cc33511c4073ae3 | B241: 8400243 | C241: BOJ - MIX - rama
A242: 676413e3b5dc26a174074c04 | B242: 8400241 | C242: CENTRO BAJO PEQUEÑO 14 | F242: 4810 Centro bajo
A243: 6764137a3857602e0502676e | B243: 8400240 | C243: PORTAVELA REDONDO 60MM | F243: 8718304332353 Soporte de vela negra
A244: 6764130b2d3f944f660114b1 | B244: 8400239 | C244: SOPORTE PLASTICO PARA VELAS VERDE | F244: 4026713057236 Soporte de vela
A245: 6764125f55ace3802b08f851 | B245: 8400238 | C245: MACETA CERAMICA - Roja | F245: Maceta roja
A246: 676411e07eaedb1bc00e3ceb | B246: 8400237 | C246: MACETA CERAMICA - pequeña | F246: Maceta marron
A247: 67640cbd9aaaef461f05dbb4 | B247: 8400236 | C247: TULIPAN - MIX -flor | F247: Tulipo, TULIRO, 37434, TULIPERO, 179100, 32652, 4046, 174305, 100948, 146775, 4566, 50454 30768, 174295, 130001, TULH, TULIPOPERO, 00020, TULIPES , 2099 TULIPAN, 32141, 38839, 138248, 173057, 11820, 5315, 1700, 5009, TUL, 173365, TULIEXTA, TULIEXPERO, TULIEXLI, TULIEXPOAM, TULIEXPOLI , 159640, 95894, 13053
A248: 676409893d72b9c4d9080a1d | B248: 8400235 | C248: NANDINA - rama | F248: NANDCAPE NANDINA CAIXA PETITA
A249: 676405f2d8b031651e0a3cf8 | B249: 8400234 | C249: MUERDAGO - rama | F249: RGUI RAMITOS MUERDAGO
A250: 6764055d17324b34a8012ad5 | B250: 8400233 | C250: ILEX - MINI- rama | F250: ILE40 ILEX 40 TALLO
A251: 676404de38e02edaf90ef69e | B251: 8400232 | C251: EUCALIPTO - Parvifolia - rama | F251: EUCE EUCALIPTO PARVIFOLIA
A252: 67602210022373b0190d1dba | B252: 8400231 | C252: [closed] GUI POMO - Nobilis - rama | F252: GUIPONOB
A253: 676021bb4d946ef81a00a92d | B253: 8400230 | C253: [closed] GUI POMO - Nordmanniana - rama | F253: GUIPONOR
... A259: 67601a8c564c896aa10ef5d8 | B259: 8400221 | C259: [closed] POINSETTIA TERRINA - planta/50 | F259: PPONSTE
A260: 675c523796b02698c901698c | B260: 8400219 | C260: Carpeta
A261: 67595ee770df18ee9f0ba46c | B261: 8400216 | C261: [deleted]COL FUCSIA - flor | F261: COLFU
A262: 67595e67c4d7cb40080609f5 | B262: 8400215 | C262: DELPHINIUM - MIX - flor | F262: delfinium DELPDO60LIFO, 73238, 100959, 100959, 171402, 117066, 179976, 30737, 59184, 131268, 2316
A263: 67595df6e345f4d8d80dccf7 | B263: 8400214 | C263: [deleted] ASTER BOLA 70 cm -flor | F263: ASTE70LICL, 115869, 30491, 34395
A264: 67595d069d47cd97eb04fd84 | B264: 8400213 | C264: ROSA PINK MONDIAL - flor | F264: RPINKMO70, 63992, 153964, 180737, 177338, 177340, 73807, 177164, 56708
A265: 67595c1136e09460d80826cb | B265: 8400212 | C265: ILEX 60-80cm - rama | F265: ILEX80
A266: 675952a8b2acbcfaa1051766 | B266: 8400211 | C266: MUSGO - caja | F266: MOLSVD MOLSA, MUSGO EN CAJA, 52421
A267: 6759523d7ed8c91b45081883 | B267: 8400210 | C267: [closed] GUI POMO NOBILIS -rama | F267: GUIPONOBSB
A268: 67595182617014a22d044a2e | B268: 8400209 | C268: CORNUS - MINI - palo | F268: CORNVE, CORNPRVE CORNUS
A269: 67585b53a64738dbe3022c32 | B269: 8400208 | C269: CORONA 25cm | F269: COROSE25
A270: 67585ad97a84546f760f1876 | B270: 8400207 | C270: CORONA 30cm | F270: COROSE30
A271: 67585a65cf25e441f9027e32 | B271: 8400206 | C271: [closed] CORONA 50cm | F271: COROSE50
A272: 675859b81dd59f825d01468d | B272: 8400205 | C272: PINYA -unidad | F272: PINYCAGR
... A282: 675811a3b10a107d130b45cd | B282: 8400195 | C282: ABETO - Nobilis - rama | F282: NOB
A283: 67507df804cd3b66270a8906 | B283: 8400194 | C283: [deleted] HELECHO - hoja
A284: 67507bf360365f13f101c5b1 | B284: 8400193 | C284: POINSETTIA COLOR MIX - planta/22 T-14 | F284: PPONSCO14, 48739 165963 104777,
A285: 67507b3c603cd1ca9f0e82b8 | B285: 8400192 | C285: [closed] POINSETTIA T-17 - planta/25 | F285: PPONS17
A286: 6750645dd8ea4c9e950e014b | B286: 8400191 | C286: MAGNOLIA - rama | F286: MAGN, 69031
A287: 6750631899aa9599f80e03ea | B287: 8400190 | C287: PHLEBODIUM - hoja | F287: FALGGR
A288: 67505c7355ea5ab13d096aa3 | B288: 8400189 | C288: [closed] POINSETTIA DE ARBOL - planta/75 | F288: PONAR
A289: 67505c28825fcb5f4c0c30e6 | B289: 8400188 | C289: [closed] CICLAMEN MINI - planta/7 | F289: CYCL11H, PCICM, cyclamen CICLAMEN MINI
A290: 67505a1e99e763726e062ab4 | B290: 8400187 | C290: POINSETTIA COLOR - MIX - planta/12 | F290: PPONC, PON, PPONP, 104183
...

Sheet Lookup
A2: Фактура 1 | B2: M | C2: Muntaner | D2: =IFERROR(__xludf.DUMMYFUNCTION("IFERROR(FILTER(products!B2:B4117 & "" - "" & products!C2:C4117 & "" ("" & products!F2:F4117 & "")"" , (REGEXMATCH(products!C2:C4117, "".*"" & A1 & "".*"") + REGEXMATCH(products!F2:F4117, "".*"" & A1 & "".*"")) > 0) , ""Нет результатов"")"),"8400916 - CILINDRO CRISTAL 155XH350MM (YE6000760)") -> 8400916 - CILINDRO CRISTAL 155XH350MM (YE6000760)
A3: Фактура 2 | B3: P | C3: Plaza | D3: =IFERROR(__xludf.DUMMYFUNCTION("""COMPUTED_VALUE"""),"R00038 - MARCADOR ( rotulador)") -> R00038 - MARCADOR ( rotulador)
A4: Фактура 3 | B4: A | C4: Augusta | D4: =IFERROR(__xludf.DUMMYFUNCTION("""COMPUTED_VALUE"""),"R00037 - BOLIGRAFO ( )") -> R00037 - BOLIGRAFO ( )
A5: Фактура 4 | B5: G | C5: Gloria | D5: =IFERROR(__xludf.DUMMYFUNCTION("""COMPUTED_VALUE"""),"R00036 - TRAPO PARA FREGONA ( )") -> R00036 - TRAPO PARA FREGONA ( )
A6: Фактура 5 | B6: B | C6: Blau | D6: =IFERROR(__xludf.DUMMYFUNCTION("""COMPUTED_VALUE"""),"R00035 - ESPONJA PARA LAVAR ( )") -> R00035 - ESPONJA PARA LAVAR ( )
A7: Фактура 6 | D7: =IFERROR(__xludf.DUMMYFUNCTION("""COMPUTED_VALUE"""),"R00034 - BOLSAS DE BASURA ( )") -> R00034 - BOLSAS DE BASURA ( )
A8: Фактура 7 | D8: =IFERROR(__xludf.DUMMYFUNCTION("""COMPUTED_VALUE"""),"R00033 - LIMPIACRISTALES ( )") -> R00033 - LIMPIACRISTALES ( )
A9: Фактура 8 | D9: =IFERROR(__xludf.DUMMYFUNCTION("""COMPUTED_VALUE"""),"R00032 - LIMPIADOR DE SUELOS ( )") -> R00032 - LIMPIADOR DE SUELOS ( )
A10: Фактура 9 | D10: =IFERROR(__xludf.DUMMYFUNCTION("""COMPUTED_VALUE"""),"R00031 - BAYETA DE LIMPIEZA ( )") -> R00031 - BAYETA DE LIMPIEZA ( )
A11: Фактура 10 | D11: =IFERROR(__xludf.DUMMYFUNCTION("""COMPUTED_VALUE"""),"R00030 - GUANTES FLORISTICOS ( )") -> R00030 - GUANTES FLORISTICOS ( )
A12: Фактура 11 | D12: =IFERROR(__xludf.DUMMYFUNCTION("""COMPUTED_VALUE"""),"R00029 - TOALLA DE PAPEL ( )") -> R00029 - TOALLA DE PAPEL ( )
A13: Фактура 12 | D13: =IFERROR(__xludf.DUMMYFUNCTION("""COMPUTED_VALUE"""),"R00028 - BOLSA ARAIK TAMAÑO XL (6050 8400274 8050503522105)") -> R00028 - BOLSA ARAIK TAMAÑO XL (6050 8400274 8050503522105)
A14: Фактура 13 | D14: =IFERROR(__xludf.DUMMYFUNCTION("""COMPUTED_VALUE"""),"R00027 - BOLSA ARAIK TAMAÑO M (6106 8400273)") -> R00027 - BOLSA ARAIK TAMAÑO M (6106 8400273)
A15: Фактура 14 | D15: =IFERROR(__xludf.DUMMYFUNCTION("""COMPUTED_VALUE"""),"R00026 - BOLSA ARAIK TAMAÑO S (2623)") -> R00026 - BOLSA ARAIK TAMAÑO S (2623)
A16: Фактура 15 | D16: =IFERROR(__xludf.DUMMYFUNCTION("""COMPUTED_VALUE"""),"R00025 - Albaran de traslado de mercancias ( Albaran de traslado de mercancias)") -> R00025 - Albaran de traslado de mercancias ( Albaran de traslado de mercancias)
A17: Фактура 16 | D17: =IFERROR(__xludf.DUMMYFUNCTION("""COMPUTED_VALUE"""),"R00024 - Acta de recepcion de mercancia ( Acta de recepcion de mercancia)") -> R00024 - Acta de recepcion de mercancia ( Acta de recepcion de mercancia)
A18: Фактура 17 | D18: =IFERROR(__xludf.DUMMYFUNCTION("""COMPUTED_VALUE"""),"R00023 - Etiquetas adhesivas (impresora de precios) ( Etiquetas adhesivas)") -> R00023 - Etiquetas adhesivas (impresora de precios) ( Etiquetas adhesivas)
A19: Фактура 18 | D19: =IFERROR(__xludf.DUMMYFUNCTION("""COMPUTED_VALUE"""),"R00022 - CUCHILLO FLORISTA 1UND (5024242421459, 1987-16)") -> R00022 - CUCHILLO FLORISTA 1UND (5024242421459, 1987-16)
A20: Фактура НЕПОНЯТНЫЙ ТОВАР | D20: =IFERROR(__xludf.DUMMYFUNCTION("""COMPUTED_VALUE"""),"R00021 - TIJERAS DE PODAR (8422347199018, 80523360176, 4000510982830, secadores, 32-00011)") -> R00021 - TIJERAS DE PODAR (8422347199018, 80523360176, 4000510982830, secadores, 32-00011)
D21: =IFERROR(__xludf.DUMMYFUNCTION("""COMPUTED_VALUE"""),"R00020 - TIJERAS FLORES (8719202891010, 5024242421527, 8410990001284)") -> R00020 - TIJERAS FLORES (8719202891010, 5024242421527, 8410990001284)
D22: =IFERROR(__xludf.DUMMYFUNCTION("""COMPUTED_VALUE"""),"R00019 - ADHESIVO DE SILICONA 1KG OASIS (5024242663071 ADHESIVO DE SILICONA 1KG OASIS )") -> R00019 - ADHESIVO DE SILICONA 1KG OASIS (5024242663071 ADHESIVO DE SILICONA 1KG OASIS )
D23: =IFERROR(__xludf.DUMMYFUNCTION("""COMPUTED_VALUE"""),"R00018 - PISTOLA SILICONA 80W OASIS (4000510929200 PISTOLA SILICONA 80W OASIS)") -> R00018 - PISTOLA SILICONA 80W OASIS (4000510929200 PISTOLA SILICONA 80W OASIS)
D24: =IFERROR(__xludf.DUMMYFUNCTION("""COMPUTED_VALUE"""),"R00017 - PALITOS DE BAMBU ( )") -> R00017 - PALITOS DE BAMBU ( )
D25: =IFERROR(__xludf.DUMMYFUNCTION("""COMPUTED_VALUE"""),"R00016 - CINTA ADHESIVA NEGRA ( CINTA ADHESIVA NEGRA)") -> R00016 - CINTA ADHESIVA NEGRA ( CINTA ADHESIVA NEGRA)
D26: =IFERROR(__xludf.DUMMYFUNCTION("""COMPUTED_VALUE"""),"R00015 - Hilo negro para etiquetas (8436036131531, 8436548911973)") -> R00015 - Hilo negro para etiquetas (8436036131531, 8436548911973)
D27: =IFERROR(__xludf.DUMMYFUNCTION("""COMPUTED_VALUE"""),"R00014 - CINTA ORGANZA ( CINTA ORGANZA, 2716)") -> R00014 - CINTA ORGANZA ( CINTA ORGANZA, 2716)
D28: =IFERROR(__xludf.DUMMYFUNCTION("""COMPUTED_VALUE"""),"R00013 - CELOFAN BLANCO MATE (8434329000038, 09001735070050)") -> R00013 - CELOFAN BLANCO MATE (8434329000038, 09001735070050)
D29: =IFERROR(__xludf.DUMMYFUNCTION("""COMPUTED_VALUE"""),"R00012 - CELOFAN NEGRO OPACO ( 34224323070025)") -> R00012 - CELOFAN NEGRO OPACO ( 34224323070025)
D30: =IFERROR(__xludf.DUMMYFUNCTION("""COMPUTED_VALUE"""),"R00011 - Etiquetas de marca Araik Galstyan (8400224 Etiquetas de marca Araik Galstyan)") -> R00011 - Etiquetas de marca Araik Galstyan (8400224 Etiquetas de marca Araik Galstyan)
D31: =IFERROR(__xludf.DUMMYFUNCTION("""COMPUTED_VALUE"""),"R00010 - PULVERIZADOR 1L (8711295692222 PULVERIZADOR 1L)") -> R00010 - PULVERIZADOR 1L (8711295692222 PULVERIZADOR 1L)
D32: =IFERROR(__xludf.DUMMYFUNCTION("""COMPUTED_VALUE"""),"R00009 - OASIS ESPONJA FLORAL 1 und (4000510010106, 10-01010, 1002002, 5104)") -> R00009 - OASIS ESPONJA FLORAL 1 und (4000510010106, 10-01010, 1002002, 5104)
D33: =IFERROR(__xludf.DUMMYFUNCTION("""COMPUTED_VALUE"""),"R00008 - Papel térmico en rollo (terminal) ( Papel para terminal)") -> R00008 - Papel térmico en rollo (terminal) ( Papel para terminal)
D34: =IFERROR(__xludf.DUMMYFUNCTION("""COMPUTED_VALUE"""),"R00006 - Papel blanco en rollo Fernando (PP05 Papel blanco en rollo Fernando)") -> R00006 - Papel blanco en rollo Fernando (PP05 Papel blanco en rollo Fernando)
D35: =IFERROR(__xludf.DUMMYFUNCTION("""COMPUTED_VALUE"""),"R00005 - Papel transparente en rollo (70050 Papel transparente en rollo)") -> R00005 - Papel transparente en rollo (70050 Papel transparente en rollo)
D36: =IFERROR(__xludf.DUMMYFUNCTION("""COMPUTED_VALUE"""),"R00004 - Papel blanco, negro en rollo (491901 Papel blanco en rollo)") -> R00004 - Papel blanco, negro en rollo (491901 Papel blanco en rollo)
D37: =IFERROR(__xludf.DUMMYFUNCTION("""COMPUTED_VALUE"""),"R00003 - Papel térmico en rollo 80*80 (caja) ( termoroll)") -> R00003 - Papel térmico en rollo 80*80 (caja) ( termoroll)
D38: =IFERROR(__xludf.DUMMYFUNCTION("""COMPUTED_VALUE"""),"R00002 - Etiquetas Kraft Negras 4 cm x 9 cm 100un ( Etiquetas Kraft Negras)") -> R00002 - Etiquetas Kraft Negras 4 cm x 9 cm 100un ( Etiquetas Kraft Negras)
D39: =IFERROR(__xludf.DUMMYFUNCTION("""COMPUTED_VALUE"""),"R00001 - Cuerda de Yute 1,2mm, 250m Natural Yute Twine ( Cuerda de Yute )") -> R00001 - Cuerda de Yute 1,2mm, 250m Natural Yute Twine ( Cuerda de Yute )
D40: =IFERROR(__xludf.DUMMYFUNCTION("""COMPUTED_VALUE"""),"R00058 - BANDEJA PORTA-FLORES (50398 BANDEJA PORTA-FLORES)") -> R00058 - BANDEJA PORTA-FLORES (50398 BANDEJA PORTA-FLORES)
D41: =IFERROR(__xludf.DUMMYFUNCTION("""COMPUTED_VALUE"""),"R00039 - CUBO NEGRO REDONDO DE PLASTICO ( 14109, 14110)") -> R00039 - CUBO NEGRO REDONDO DE PLASTICO ( 14109, 14110)
D42: =IFERROR(__xludf.DUMMYFUNCTION("""COMPUTED_VALUE"""),"8400007 - CESTA MIMBRE GRANDE ( )") -> 8400007 - CESTA MIMBRE GRANDE ( )
D43: =IFERROR(__xludf.DUMMYFUNCTION("""COMPUTED_VALUE"""),"8400459 - [closed] ALMENDRA con FLORES 1,5-2m - rama ( 8400459)") -> 8400459 - [closed] ALMENDRA con FLORES 1,5-2m - rama ( 8400459)
D44: =IFERROR(__xludf.DUMMYFUNCTION("""COMPUTED_VALUE"""),"8400458 - HELECHO T10 - planta/14 ( 8400458)") -> 8400458 - HELECHO T10 - planta/14 ( 8400458)
D45: =IFERROR(__xludf.DUMMYFUNCTION("""COMPUTED_VALUE"""),"8400457 - HORTENSIA T14, T15 - planta/28 (HOR, 130498, 99757, 130498, 175237, 176490,10104, 172749)") -> 8400457 - HORTENSIA T14, T15 - planta/28 (HOR, 130498, 99757, 130498, 175237, 176490,10104, 172749)
D46: =IFERROR(__xludf.DUMMYFUNCTION("""COMPUTED_VALUE"""),"8400456 - ROSA - Mondial (RSC60 8400456, 177325, 177160, 177161, 177161)") -> 8400456 - ROSA - Mondial (RSC60 8400456, 177325, 177160, 177161, 177161)
D47: =IFERROR(__xludf.DUMMYFUNCTION("""COMPUTED_VALUE"""),"8400455 - CALA MIX - planta/20 (Cala 8400455, 95, 1035, 193945)") -> 8400455 - CALA MIX - planta/20 (Cala 8400455, 95, 1035, 193945)
D48: =IFERROR(__xludf.DUMMYFUNCTION("""COMPUTED_VALUE"""),"8400454 - YUCCA 120cm - planta/165 ( YUCCA 120cm planta)") -> 8400454 - YUCCA 120cm - planta/165 ( YUCCA 120cm planta)
D49: =IFERROR(__xludf.DUMMYFUNCTION("""COMPUTED_VALUE"""),"8400453 - YUCCA 90cm - planta/135 ( YUCCA 90cm planta)") -> 8400453 - YUCCA 90cm - planta/135 ( YUCCA 90cm planta)
D50: =IFERROR(__xludf.DUMMYFUNCTION("""COMPUTED_VALUE"""),"8400452 - FICUS T20 - Benjamina - planta/35 (FICBEN20PAC FICUS BENJAMINA T-20 planta)") -> 8400452 - FICUS T20 - Benjamina - planta/35 (FICBEN20PAC FICUS BENJAMINA T-20 planta)
D51: =IFERROR(__xludf.DUMMYFUNCTION("""COMPUTED_VALUE"""),"8400451 - DRACAENA T5L- Compacta - planta/42 (dracaena DRACENA COMPACTA 5L planta)") -> 8400451 - DRACAENA T5L- Compacta - planta/42 (dracaena DRACENA COMPACTA 5L planta)
D52: =IFERROR(__xludf.DUMMYFUNCTION("""COMPUTED_VALUE"""),"8400450 - [closed] CALA T5L - planta/15 (CA21 Calla Zantedeschia Aethiopica 5L planta)") -> 8400450 - [closed] CALA T5L - planta/15 (CA21 Calla Zantedeschia Aethiopica 5L planta)
D53: =IFERROR(__xludf.DUMMYFUNCTION("""COMPUTED_VALUE"""),"8400449 - PHILODENDRON T14 - Birkin - planta/18 (PHILB, 179578, WHITE, BIRKIN PHILODENDRON BIRKIN T-14 planta)") -> 8400449 - PHILODENDRON T14 - Birkin - planta/18 (PHILB, 179578, WHITE, BIRKIN PHILODENDRON BIRKIN T-14 planta)
D54: =IFERROR(__xludf.DUMMYFUNCTION("""COMPUTED_VALUE"""),"8400448 - KALANCHOE T25 - Pumila - planta/18 (KAL-P KALANCHOE PUMILA T-25 planta, KCALT)") -> 8400448 - KALANCHOE T25 - Pumila - planta/18 (KAL-P KALANCHOE PUMILA T-25 planta, KCALT)
D55: =IFERROR(__xludf.DUMMYFUNCTION("""COMPUTED_VALUE"""),"8400447 - EUCALIPTO SECO -MIX - rama (EUCU, KUCU EUCALIPTO CINEREA TEÑIDO)") -> 8400447 - EUCALIPTO SECO -MIX - rama (EUCU, KUCU EUCALIPTO CINEREA TEÑIDO)
D56: =IFERROR(__xludf.DUMMYFUNCTION("""COMPUTED_VALUE"""),"8400443 - [closed] SUCCULENTUS T8 - MIX - planta/6 (CRASSULACEAE, CRA8 Succulentus MIX T-8 planta)") -> 8400443 - [closed] SUCCULENTUS T8 - MIX - planta/6 (CRASSULACEAE, CRA8 Succulentus MIX T-8 planta)
D57: =IFERROR(__xludf.DUMMYFUNCTION("""COMPUTED_VALUE"""),"8400442 - EUPHORBIA T18 - Eritrea - planta/79 (EUPH18 EUPHORBIA ERITREA T-18 planta)") -> 8400442 - EUPHORBIA T18 - Eritrea - planta/79 (EUPH18 EUPHORBIA ERITREA T-18 planta)
D58: =IFERROR(__xludf.DUMMYFUNCTION("""COMPUTED_VALUE"""),"8400441 - [closed] CAMPANULA T11 - planta/7 (CAMPA11H CAMPANULA T-11 planta)") -> 8400441 - [closed] CAMPANULA T11 - planta/7 (CAMPA11H CAMPANULA T-11 planta)
D59: =IFERROR(__xludf.DUMMYFUNCTION("""COMPUTED_VALUE"""),"8400440 - DIEFFENBACHIA T12 MIX - planta/12 (DIEF DIEFFENBACCHIA MIX T-12 planta)") -> 8400440 - DIEFFENBACHIA T12 MIX - planta/12 (DIEF DIEFFENBACCHIA MIX T-12 planta)
D60: =IFERROR(__xludf.DUMMYFUNCTION("""COMPUTED_VALUE"""),"8400439 - [deleted] DENDROBIUM MIX T-12 planta (DEND DENDROBIUM MIX T-12 planta)") -> 8400439 - [deleted] DENDROBIUM MIX T-12 planta (DEND DENDROBIUM MIX T-12 planta)
D61: =IFERROR(__xludf.DUMMYFUNCTION("""COMPUTED_VALUE"""),"8400438 - PACHIRA T9 - planta/18 (PACH9 PACHIRA T-9 planta)") -> 8400438 - PACHIRA T9 - planta/18 (PACH9 PACHIRA T-9 planta)
D62: =IFERROR(__xludf.DUMMYFUNCTION("""COMPUTED_VALUE"""),"8400437 - FICUS T26 - Tineke - planta/89 (FTI26 FICUS TINEKE T-26 planta)") -> 8400437 - FICUS T26 - Tineke - planta/89 (FTI26 FICUS TINEKE T-26 planta)
D63: =IFERROR(__xludf.DUMMYFUNCTION("""COMPUTED_VALUE"""),"8400436 - [deleted] ANTHURIUM MICRA T-12 planta (MIC12 ANTHURIUM MICRA T-12 planta, )") -> 8400436 - [deleted] ANTHURIUM MICRA T-12 planta (MIC12 ANTHURIUM MICRA T-12 planta, )
D64: =IFERROR(__xludf.DUMMYFUNCTION("""COMPUTED_VALUE"""),"8400435 - BEGONIA T20 - Maculata - planta/42 (1096 BEGONIA MACULATA T-20 planta)") -> 8400435 - BEGONIA T20 - Maculata - planta/42 (1096 BEGONIA MACULATA T-20 planta)
D65: =IFERROR(__xludf.DUMMYFUNCTION("""COMPUTED_VALUE"""),"8400434 - DIPLADEMIA - planta/25 ( DIPLODEMIA planta)") -> 8400434 - DIPLADEMIA - planta/25 ( DIPLODEMIA planta)
D66: =IFERROR(__xludf.DUMMYFUNCTION("""COMPUTED_VALUE"""),"8400433 - IRIS - flor (IRIA IRIS de corte IRI, 53473, 33546)") -> 8400433 - IRIS - flor (IRIA IRIS de corte IRI, 53473, 33546)
D67: =IFERROR(__xludf.DUMMYFUNCTION("""COMPUTED_VALUE"""),"8400432 - PANICULATA - rama ( PANICULATA rama pequeña, 29334, 18949, 53191, 54564, 100223, 49125, 49125, 100429, 141319, 92513, 130670, 67464 PAN, 18798, 101047)") -> 8400432 - PANICULATA - rama ( PANICULATA rama pequeña, 29334, 18949, 53191, 54564, 100223, 49125, 49125, 100429, 141319, 92513, 130670, 67464 PAN, 18798, 101047)
D68: =IFERROR(__xludf.DUMMYFUNCTION("""COMPUTED_VALUE"""),"8400431 - FORSYTHIA - rama (2121 FORSYTHIA RAMA 60 cm)") -> 8400431 - FORSYTHIA - rama (2121 FORSYTHIA RAMA 60 cm)
D69: =IFERROR(__xludf.DUMMYFUNCTION("""COMPUTED_VALUE"""),"8400430 - MAGNOLIA con BROTES- rama (9514 MAGNOLIA RAMA 50 cm)") -> 8400430 - MAGNOLIA con BROTES- rama (9514 MAGNOLIA RAMA 50 cm)
D70: =IFERROR(__xludf.DUMMYFUNCTION("""COMPUTED_VALUE"""),"8400429 - ESCABIOSA HOLANDA - flor ( ESCABIOSA HOLANDA, 135562, 129766)") -> 8400429 - ESCABIOSA HOLANDA - flor ( ESCABIOSA HOLANDA, 135562, 129766)
D71: =IFERROR(__xludf.DUMMYFUNCTION("""COMPUTED_VALUE"""),"8400428 - CYMBIDIUM 4V - planta/75 (PL.CYM CYMBIDIUM 4-RAMA PLANTA CYM4V)") -> 8400428 - CYMBIDIUM 4V - planta/75 (PL.CYM CYMBIDIUM 4-RAMA PLANTA CYM4V)
D72: =IFERROR(__xludf.DUMMYFUNCTION("""COMPUTED_VALUE"""),"8400427 - CORTADERIA - herbacea ( CORTADERIA RAMA)") -> 8400427 - CORTADERIA - herbacea ( CORTADERIA RAMA)
D73: =IFERROR(__xludf.DUMMYFUNCTION("""COMPUTED_VALUE"""),"8400426 - NARCISO - flor (NAD, NADAL, NADALES, NARCISSUS , 48711, 39962)") -> 8400426 - NARCISO - flor (NAD, NADAL, NADALES, NARCISSUS , 48711, 39962)
D74: =IFERROR(__xludf.DUMMYFUNCTION("""COMPUTED_VALUE"""),"8400425 - [closed] FRESIA - flor (FRE FRESIA de corte)") -> 8400425 - [closed] FRESIA - flor (FRE FRESIA de corte)
D75: =IFERROR(__xludf.DUMMYFUNCTION("""COMPUTED_VALUE"""),"8400424 - [closed] RS ROSA - Flamingo ( ROSA FLAMINGO)") -> 8400424 - [closed] RS ROSA - Flamingo ( ROSA FLAMINGO)
D76: =IFERROR(__xludf.DUMMYFUNCTION("""COMPUTED_VALUE"""),"8400423 - [closed] ALMENDRA con FLORES - MINI - rama ( ALMENDRA CON FLORES RAMA PEQUEÑA)") -> 8400423 - [closed] ALMENDRA con FLORES - MINI - rama ( ALMENDRA CON FLORES RAMA PEQUEÑA)
D77: =IFERROR(__xludf.DUMMYFUNCTION("""COMPUTED_VALUE"""),"8400422 - [closed] LAUREL - MINI - rama ( LAUREL RAMA PEQUEÑA)") -> 8400422 - [closed] LAUREL - MINI - rama ( LAUREL RAMA PEQUEÑA)
D78: =IFERROR(__xludf.DUMMYFUNCTION("""COMPUTED_VALUE"""),"8400421 - [closed] LAUREL - rama ( LAUREL RAMA GRANDE)") -> 8400421 - [closed] LAUREL - rama ( LAUREL RAMA GRANDE)
D79: =IFERROR(__xludf.DUMMYFUNCTION("""COMPUTED_VALUE"""),"8400420 - [closed] HIEDRA (HEDERA) - MIX - planta/25 ( HIEDRA MIX planta)") -> 8400420 - [closed] HIEDRA (HEDERA) - MIX - planta/25 ( HIEDRA MIX planta)
D80: =IFERROR(__xludf.DUMMYFUNCTION("""COMPUTED_VALUE"""),"8400419 - [closed] RS ROSA - Clarence (4452 Rosa Clarence 70 cm Naranja)") -> 8400419 - [closed] RS ROSA - Clarence (4452 Rosa Clarence 70 cm Naranja)
D81: =IFERROR(__xludf.DUMMYFUNCTION("""COMPUTED_VALUE"""),"8400418 - ORNITHOGALUM - flor (JACIPO ORNITHOGALUM)") -> 8400418 - ORNITHOGALUM - flor (JACIPO ORNITHOGALUM)
D82: =IFERROR(__xludf.DUMMYFUNCTION("""COMPUTED_VALUE"""),"8400417 - [closed] MACETA ANTIGUA ( MACETA ANTIGUA)") -> 8400417 - [closed] MACETA ANTIGUA ( MACETA ANTIGUA)
D83: =IFERROR(__xludf.DUMMYFUNCTION("""COMPUTED_VALUE"""),"8400416 - [closed] LIMONERO T20 - planta/100 (LLI20 LLIMONER T-20 planta)") -> 8400416 - [closed] LIMONERO T20 - planta/100 (LLI20 LLIMONER T-20 planta)
D84: =IFERROR(__xludf.DUMMYFUNCTION("""COMPUTED_VALUE"""),"8400415 - RHIPSALIS GRANDE - planta/95 (RHI9 RHIPSALIS GRANDE planta)") -> 8400415 - RHIPSALIS GRANDE - planta/95 (RHI9 RHIPSALIS GRANDE planta)
D85: =IFERROR(__xludf.DUMMYFUNCTION("""COMPUTED_VALUE"""),"8400413 - ALOCASIA T12 - Frydek - planta/15 (ALOF ALOCASIA FRYDEK T-12 planta)") -> 8400413 - ALOCASIA T12 - Frydek - planta/15 (ALOF ALOCASIA FRYDEK T-12 planta)
D86: =IFERROR(__xludf.DUMMYFUNCTION("""COMPUTED_VALUE"""),"8400412 - EUPHORBIA T20 - Eritrea - planta/110 (EUPH20 EUPHORBIA ERITREA T-20 planta)") -> 8400412 - EUPHORBIA T20 - Eritrea - planta/110 (EUPH20 EUPHORBIA ERITREA T-20 planta)
D87: =IFERROR(__xludf.DUMMYFUNCTION("""COMPUTED_VALUE"""),"8400411 - EUPHORBIA - Eritrea Extra - planta/125 (EUP30 EUPHORBIA ERITREA T-30 planta, 6EUPT080, 4022314 46, TIRUCALLI 10L)") -> 8400411 - EUPHORBIA - Eritrea Extra - planta/125 (EUP30 EUPHORBIA ERITREA T-30 planta, 6EUPT080, 4022314 46, TIRUCALLI 10L)
D88: =IFERROR(__xludf.DUMMYFUNCTION("""COMPUTED_VALUE"""),"8400410 - SUCCULENTUS T16, T22 - MIX - planta/22 (6CRASA22, 54, CRASS16 )") -> 8400410 - SUCCULENTUS T16, T22 - MIX - planta/22 (6CRASA22, 54, CRASS16 )
D89: =IFERROR(__xludf.DUMMYFUNCTION("""COMPUTED_VALUE"""),"8400409 - SUCCULENTUS T13 - MIX - planta/8 (GORASA13, 52б crasa, 172028, CRA13, crassulaceae Succulentus MIX T-13 planta, CRA, SED, LAEON. 011, Aeonium arboreum m13)") -> 8400409 - SUCCULENTUS T13 - MIX - planta/8 (GORASA13, 52б crasa, 172028, CRA13, crassulaceae Succulentus MIX T-13 planta, CRA, SED, LAEON. 011, Aeonium arboreum m13)
D90: =IFERROR(__xludf.DUMMYFUNCTION("""COMPUTED_VALUE"""),"8400408 - SUCCULENTUS T20 - MIX - planta/15 (6GRASA20, 53, crasa, 6CRASA20, A70100, CRA17)") -> 8400408 - SUCCULENTUS T20 - MIX - planta/15 (6GRASA20, 53, crasa, 6CRASA20, A70100, CRA17)
D91: =IFERROR(__xludf.DUMMYFUNCTION("""COMPUTED_VALUE"""),"8400407 - ROMERO T5L - planta/15 (DROMO05L ROSMARINUS OFFICINALIS 5L planta)") -> 8400407 - ROMERO T5L - planta/15 (DROMO05L ROSMARINUS OFFICINALIS 5L planta)
D92: =IFERROR(__xludf.DUMMYFUNCTION("""COMPUTED_VALUE"""),"8400404 - CALATHEA T19 - planta/54 (CALM19 CALATHEA MIX T-19 planta, 128628)") -> 8400404 - CALATHEA T19 - planta/54 (CALM19 CALATHEA MIX T-19 planta, 128628)
D93: =IFERROR(__xludf.DUMMYFUNCTION("""COMPUTED_VALUE"""),"8400403 - [closed] KALANCHOE T22 - Tessa - planta/35 (KAL-22 KALANCHOE TESSA T-22 planta)") -> 8400403 - [closed] KALANCHOE T22 - Tessa - planta/35 (KAL-22 KALANCHOE TESSA T-22 planta)
D94: =IFERROR(__xludf.DUMMYFUNCTION("""COMPUTED_VALUE"""),"8400402 - OXYPETALUM (TVIDYA) - flor ( OXYPETALUM, 83266, 112967)") -> 8400402 - OXYPETALUM (TVIDYA) - flor ( OXYPETALUM, 83266, 112967)
D95: =IFERROR(__xludf.DUMMYFUNCTION("""COMPUTED_VALUE"""),"8400401 - ANEMONA - flor ( ANEMONA, 9445, 74232, 145198, 149541, )") -> 8400401 - ANEMONA - flor ( ANEMONA, 9445, 74232, 145198, 149541, )
D96: =IFERROR(__xludf.DUMMYFUNCTION("""COMPUTED_VALUE"""),"8400400 - [closed] STRELITZIA con FLORES - rama (ESTERLITZIA STRELITZIA hojas con flores)") -> 8400400 - [closed] STRELITZIA con FLORES - rama (ESTERLITZIA STRELITZIA hojas con flores)
D97: =IFERROR(__xludf.DUMMYFUNCTION("""COMPUTED_VALUE"""),"8400399 - RSR ROSA RAMI - MIX (7929-54 ROSA RAMIFICADA Assorte, 498, 19736 180319 38529 9451)") -> 8400399 - RSR ROSA RAMI - MIX (7929-54 ROSA RAMIFICADA Assorte, 498, 19736 180319 38529 9451)
D98: =IFERROR(__xludf.DUMMYFUNCTION("""COMPUTED_VALUE"""),"8400398 - [closed] OLIVO - rama ( OLIVA)") -> 8400398 - [closed] OLIVO - rama ( OLIVA)
D99: =IFERROR(__xludf.DUMMYFUNCTION("""COMPUTED_VALUE"""),"8400397 - [deleted] Ricinus con flor - rama ( Ricinus con flor)") -> 8400397 - [deleted] Ricinus con flor - rama ( Ricinus con flor)
D100: =IFERROR(__xludf.DUMMYFUNCTION("""COMPUTED_VALUE"""),"8400396 - [closed] RICINUS -rama ( Ricinus Grande)") -> 8400396 - [closed] RICINUS -rama ( Ricinus Grande)
D101: =IFERROR(__xludf.DUMMYFUNCTION("""COMPUTED_VALUE"""),"8400395 - MARFULL - Arbol- rama ( Marful Arbol (Rama))") -> 8400395 - MARFULL - Arbol- rama ( Marful Arbol (Rama))
...
